{"neighbourhood_id":1,"population_density_Rank":155.0,"population_by_gender_Data_Male_Rank":158.0,"population_by_gender_Data_Female_Rank":171.0,"Age_Diversity_Index_Rank":88.0,"Employment_Health_Index_Rank":12.0,"Annual_Earnings_Index_Rank":80.0,"Housing_Affordability_Index_Rank":134.0,"Crime_Rate_Index_Rank":120.0,"Young_Index_Rank":176.0,"Middle_Aged_Index_Rank":157.0,"Old_Index_Rank":187.0}
{"neighbourhood_id":7,"population_density_Rank":88.0,"population_by_gender_Data_Male_Rank":152.0,"population_by_gender_Data_Female_Rank":139.0,"Age_Diversity_Index_Rank":128.0,"Employment_Health_Index_Rank":81.0,"Annual_Earnings_Index_Rank":160.0,"Housing_Affordability_Index_Rank":69.0,"Crime_Rate_Index_Rank":115.0,"Young_Index_Rank":109.0,"Middle_Aged_Index_Rank":179.0,"Old_Index_Rank":204.0}
{"neighbourhood_id":5,"population_density_Rank":115.0,"population_by_gender_Data_Male_Rank":115.0,"population_by_gender_Data_Female_Rank":114.0,"Age_Diversity_Index_Rank":85.0,"Employment_Health_Index_Rank":19.0,"Annual_Earnings_Index_Rank":28.0,"Housing_Affordability_Index_Rank":76.0,"Crime_Rate_Index_Rank":86.0,"Young_Index_Rank":130.0,"Middle_Aged_Index_Rank":97.0,"Old_Index_Rank":118.0}
{"neighbourhood_id":2,"population_density_Rank":105.0,"population_by_gender_Data_Male_Rank":14.0,"population_by_gender_Data_Female_Rank":28.0,"Age_Diversity_Index_Rank":24.0,"Employment_Health_Index_Rank":45.0,"Annual_Earnings_Index_Rank":11.0,"Housing_Affordability_Index_Rank":8.0,"Crime_Rate_Index_Rank":58.0,"Young_Index_Rank":10.0,"Middle_Aged_Index_Rank":49.0,"Old_Index_Rank":81.0}
{"neighbourhood_id":8,"population_density_Rank":88.0,"population_by_gender_Data_Male_Rank":152.0,"population_by_gender_Data_Female_Rank":139.0,"Age_Diversity_Index_Rank":128.0,"Employment_Health_Index_Rank":81.0,"Annual_Earnings_Index_Rank":160.0,"Housing_Affordability_Index_Rank":69.0,"Crime_Rate_Index_Rank":115.0,"Young_Index_Rank":109.0,"Middle_Aged_Index_Rank":179.0,"Old_Index_Rank":204.0}
{"neighbourhood_id":3,"population_density_Rank":105.0,"population_by_gender_Data_Male_Rank":14.0,"population_by_gender_Data_Female_Rank":28.0,"Age_Diversity_Index_Rank":24.0,"Employment_Health_Index_Rank":45.0,"Annual_Earnings_Index_Rank":11.0,"Housing_Affordability_Index_Rank":8.0,"Crime_Rate_Index_Rank":58.0,"Young_Index_Rank":10.0,"Middle_Aged_Index_Rank":49.0,"Old_Index_Rank":81.0}
{"neighbourhood_id":10,"population_density_Rank":52.0,"population_by_gender_Data_Male_Rank":108.0,"population_by_gender_Data_Female_Rank":104.0,"Age_Diversity_Index_Rank":121.0,"Employment_Health_Index_Rank":76.0,"Annual_Earnings_Index_Rank":75.0,"Housing_Affordability_Index_Rank":54.0,"Crime_Rate_Index_Rank":61.0,"Young_Index_Rank":98.0,"Middle_Aged_Index_Rank":104.0,"Old_Index_Rank":137.0}
{"neighbourhood_id":6,"population_density_Rank":115.0,"population_by_gender_Data_Male_Rank":115.0,"population_by_gender_Data_Female_Rank":114.0,"Age_Diversity_Index_Rank":85.0,"Employment_Health_Index_Rank":19.0,"Annual_Earnings_Index_Rank":28.0,"Housing_Affordability_Index_Rank":76.0,"Crime_Rate_Index_Rank":86.0,"Young_Index_Rank":130.0,"Middle_Aged_Index_Rank":97.0,"Old_Index_Rank":118.0}
{"neighbourhood_id":4,"population_density_Rank":105.0,"population_by_gender_Data_Male_Rank":14.0,"population_by_gender_Data_Female_Rank":28.0,"Age_Diversity_Index_Rank":24.0,"Employment_Health_Index_Rank":45.0,"Annual_Earnings_Index_Rank":11.0,"Housing_Affordability_Index_Rank":8.0,"Crime_Rate_Index_Rank":58.0,"Young_Index_Rank":10.0,"Middle_Aged_Index_Rank":49.0,"Old_Index_Rank":81.0}
{"neighbourhood_id":9,"population_density_Rank":88.0,"population_by_gender_Data_Male_Rank":152.0,"population_by_gender_Data_Female_Rank":139.0,"Age_Diversity_Index_Rank":128.0,"Employment_Health_Index_Rank":81.0,"Annual_Earnings_Index_Rank":160.0,"Housing_Affordability_Index_Rank":69.0,"Crime_Rate_Index_Rank":115.0,"Young_Index_Rank":109.0,"Middle_Aged_Index_Rank":179.0,"Old_Index_Rank":204.0}
{"neighbourhood_id":11,"population_density_Rank":52.0,"population_by_gender_Data_Male_Rank":108.0,"population_by_gender_Data_Female_Rank":104.0,"Age_Diversity_Index_Rank":121.0,"Employment_Health_Index_Rank":76.0,"Annual_Earnings_Index_Rank":75.0,"Housing_Affordability_Index_Rank":54.0,"Crime_Rate_Index_Rank":61.0,"Young_Index_Rank":98.0,"Middle_Aged_Index_Rank":104.0,"Old_Index_Rank":137.0}
{"neighbourhood_id":12,"population_density_Rank":73.0,"population_by_gender_Data_Male_Rank":103.0,"population_by_gender_Data_Female_Rank":129.0,"Age_Diversity_Index_Rank":77.0,"Employment_Health_Index_Rank":126.0,"Annual_Earnings_Index_Rank":167.0,"Housing_Affordability_Index_Rank":126.0,"Crime_Rate_Index_Rank":54.0,"Young_Index_Rank":81.0,"Middle_Aged_Index_Rank":134.0,"Old_Index_Rank":202.0}
{"neighbourhood_id":13,"population_density_Rank":124.0,"population_by_gender_Data_Male_Rank":22.0,"population_by_gender_Data_Female_Rank":10.0,"Age_Diversity_Index_Rank":16.0,"Employment_Health_Index_Rank":203.0,"Annual_Earnings_Index_Rank":73.0,"Housing_Affordability_Index_Rank":11.0,"Crime_Rate_Index_Rank":5.0,"Young_Index_Rank":8.0,"Middle_Aged_Index_Rank":27.0,"Old_Index_Rank":56.0}
{"neighbourhood_id":15,"population_density_Rank":142.0,"population_by_gender_Data_Male_Rank":17.0,"population_by_gender_Data_Female_Rank":12.0,"Age_Diversity_Index_Rank":5.0,"Employment_Health_Index_Rank":226.0,"Annual_Earnings_Index_Rank":68.0,"Housing_Affordability_Index_Rank":47.0,"Crime_Rate_Index_Rank":134.0,"Young_Index_Rank":5.0,"Middle_Aged_Index_Rank":24.0,"Old_Index_Rank":86.0}
{"neighbourhood_id":16,"population_density_Rank":124.0,"population_by_gender_Data_Male_Rank":22.0,"population_by_gender_Data_Female_Rank":10.0,"Age_Diversity_Index_Rank":16.0,"Employment_Health_Index_Rank":203.0,"Annual_Earnings_Index_Rank":73.0,"Housing_Affordability_Index_Rank":11.0,"Crime_Rate_Index_Rank":5.0,"Young_Index_Rank":8.0,"Middle_Aged_Index_Rank":27.0,"Old_Index_Rank":56.0}
{"neighbourhood_id":17,"population_density_Rank":142.0,"population_by_gender_Data_Male_Rank":17.0,"population_by_gender_Data_Female_Rank":12.0,"Age_Diversity_Index_Rank":5.0,"Employment_Health_Index_Rank":226.0,"Annual_Earnings_Index_Rank":68.0,"Housing_Affordability_Index_Rank":47.0,"Crime_Rate_Index_Rank":134.0,"Young_Index_Rank":5.0,"Middle_Aged_Index_Rank":24.0,"Old_Index_Rank":86.0}
{"neighbourhood_id":18,"population_density_Rank":158.0,"population_by_gender_Data_Male_Rank":227.0,"population_by_gender_Data_Female_Rank":221.0,"Age_Diversity_Index_Rank":192.0,"Employment_Health_Index_Rank":235.0,"Annual_Earnings_Index_Rank":227.0,"Housing_Affordability_Index_Rank":119.0,"Crime_Rate_Index_Rank":143.0,"Young_Index_Rank":226.0,"Middle_Aged_Index_Rank":225.0,"Old_Index_Rank":189.0}
{"neighbourhood_id":19,"population_density_Rank":142.0,"population_by_gender_Data_Male_Rank":17.0,"population_by_gender_Data_Female_Rank":12.0,"Age_Diversity_Index_Rank":5.0,"Employment_Health_Index_Rank":226.0,"Annual_Earnings_Index_Rank":68.0,"Housing_Affordability_Index_Rank":47.0,"Crime_Rate_Index_Rank":134.0,"Young_Index_Rank":5.0,"Middle_Aged_Index_Rank":24.0,"Old_Index_Rank":86.0}
{"neighbourhood_id":21,"population_density_Rank":160.0,"population_by_gender_Data_Male_Rank":182.0,"population_by_gender_Data_Female_Rank":181.0,"Age_Diversity_Index_Rank":146.0,"Employment_Health_Index_Rank":17.0,"Annual_Earnings_Index_Rank":121.0,"Housing_Affordability_Index_Rank":93.0,"Crime_Rate_Index_Rank":108.0,"Young_Index_Rank":186.0,"Middle_Aged_Index_Rank":170.0,"Old_Index_Rank":200.0}
{"neighbourhood_id":22,"population_density_Rank":138.0,"population_by_gender_Data_Male_Rank":75.0,"population_by_gender_Data_Female_Rank":81.0,"Age_Diversity_Index_Rank":33.0,"Employment_Health_Index_Rank":7.0,"Annual_Earnings_Index_Rank":1.0,"Housing_Affordability_Index_Rank":121.0,"Crime_Rate_Index_Rank":149.0,"Young_Index_Rank":107.0,"Middle_Aged_Index_Rank":57.0,"Old_Index_Rank":129.0}
{"neighbourhood_id":23,"population_density_Rank":66.0,"population_by_gender_Data_Male_Rank":45.0,"population_by_gender_Data_Female_Rank":62.0,"Age_Diversity_Index_Rank":110.0,"Employment_Health_Index_Rank":54.0,"Annual_Earnings_Index_Rank":43.0,"Housing_Affordability_Index_Rank":130.0,"Crime_Rate_Index_Rank":103.0,"Young_Index_Rank":46.0,"Middle_Aged_Index_Rank":52.0,"Old_Index_Rank":78.0}
{"neighbourhood_id":24,"population_density_Rank":165.0,"population_by_gender_Data_Male_Rank":183.0,"population_by_gender_Data_Female_Rank":201.0,"Age_Diversity_Index_Rank":166.0,"Employment_Health_Index_Rank":43.0,"Annual_Earnings_Index_Rank":210.0,"Housing_Affordability_Index_Rank":181.0,"Crime_Rate_Index_Rank":121.0,"Young_Index_Rank":177.0,"Middle_Aged_Index_Rank":197.0,"Old_Index_Rank":223.0}
{"neighbourhood_id":25,"population_density_Rank":60.0,"population_by_gender_Data_Male_Rank":4.0,"population_by_gender_Data_Female_Rank":17.0,"Age_Diversity_Index_Rank":52.0,"Employment_Health_Index_Rank":90.0,"Annual_Earnings_Index_Rank":61.0,"Housing_Affordability_Index_Rank":61.0,"Crime_Rate_Index_Rank":51.0,"Young_Index_Rank":13.0,"Middle_Aged_Index_Rank":12.0,"Old_Index_Rank":48.0}
{"neighbourhood_id":27,"population_density_Rank":86.0,"population_by_gender_Data_Male_Rank":121.0,"population_by_gender_Data_Female_Rank":116.0,"Age_Diversity_Index_Rank":82.0,"Employment_Health_Index_Rank":10.0,"Annual_Earnings_Index_Rank":37.0,"Housing_Affordability_Index_Rank":108.0,"Crime_Rate_Index_Rank":127.0,"Young_Index_Rank":126.0,"Middle_Aged_Index_Rank":109.0,"Old_Index_Rank":148.0}
{"neighbourhood_id":28,"population_density_Rank":49.0,"population_by_gender_Data_Male_Rank":78.0,"population_by_gender_Data_Female_Rank":74.0,"Age_Diversity_Index_Rank":123.0,"Employment_Health_Index_Rank":187.0,"Annual_Earnings_Index_Rank":110.0,"Housing_Affordability_Index_Rank":32.0,"Crime_Rate_Index_Rank":22.0,"Young_Index_Rank":61.0,"Middle_Aged_Index_Rank":93.0,"Old_Index_Rank":95.0}
{"neighbourhood_id":29,"population_density_Rank":49.0,"population_by_gender_Data_Male_Rank":78.0,"population_by_gender_Data_Female_Rank":74.0,"Age_Diversity_Index_Rank":123.0,"Employment_Health_Index_Rank":187.0,"Annual_Earnings_Index_Rank":110.0,"Housing_Affordability_Index_Rank":32.0,"Crime_Rate_Index_Rank":22.0,"Young_Index_Rank":61.0,"Middle_Aged_Index_Rank":93.0,"Old_Index_Rank":95.0}
{"neighbourhood_id":30,"population_density_Rank":49.0,"population_by_gender_Data_Male_Rank":78.0,"population_by_gender_Data_Female_Rank":74.0,"Age_Diversity_Index_Rank":123.0,"Employment_Health_Index_Rank":187.0,"Annual_Earnings_Index_Rank":110.0,"Housing_Affordability_Index_Rank":32.0,"Crime_Rate_Index_Rank":22.0,"Young_Index_Rank":61.0,"Middle_Aged_Index_Rank":93.0,"Old_Index_Rank":95.0}
{"neighbourhood_id":31,"population_density_Rank":45.0,"population_by_gender_Data_Male_Rank":107.0,"population_by_gender_Data_Female_Rank":95.0,"Age_Diversity_Index_Rank":134.0,"Employment_Health_Index_Rank":78.0,"Annual_Earnings_Index_Rank":87.0,"Housing_Affordability_Index_Rank":98.0,"Crime_Rate_Index_Rank":76.0,"Young_Index_Rank":97.0,"Middle_Aged_Index_Rank":96.0,"Old_Index_Rank":105.0}
{"neighbourhood_id":32,"population_density_Rank":132.0,"population_by_gender_Data_Male_Rank":66.0,"population_by_gender_Data_Female_Rank":72.0,"Age_Diversity_Index_Rank":94.0,"Employment_Health_Index_Rank":106.0,"Annual_Earnings_Index_Rank":22.0,"Housing_Affordability_Index_Rank":122.0,"Crime_Rate_Index_Rank":167.0,"Young_Index_Rank":93.0,"Middle_Aged_Index_Rank":46.0,"Old_Index_Rank":28.0}
{"neighbourhood_id":33,"population_density_Rank":139.0,"population_by_gender_Data_Male_Rank":135.0,"population_by_gender_Data_Female_Rank":137.0,"Age_Diversity_Index_Rank":153.0,"Employment_Health_Index_Rank":178.0,"Annual_Earnings_Index_Rank":127.0,"Housing_Affordability_Index_Rank":196.0,"Crime_Rate_Index_Rank":171.0,"Young_Index_Rank":156.0,"Middle_Aged_Index_Rank":132.0,"Old_Index_Rank":89.0}
{"neighbourhood_id":34,"population_density_Rank":132.0,"population_by_gender_Data_Male_Rank":66.0,"population_by_gender_Data_Female_Rank":72.0,"Age_Diversity_Index_Rank":94.0,"Employment_Health_Index_Rank":106.0,"Annual_Earnings_Index_Rank":22.0,"Housing_Affordability_Index_Rank":122.0,"Crime_Rate_Index_Rank":167.0,"Young_Index_Rank":93.0,"Middle_Aged_Index_Rank":46.0,"Old_Index_Rank":28.0}
{"neighbourhood_id":35,"population_density_Rank":139.0,"population_by_gender_Data_Male_Rank":135.0,"population_by_gender_Data_Female_Rank":137.0,"Age_Diversity_Index_Rank":153.0,"Employment_Health_Index_Rank":178.0,"Annual_Earnings_Index_Rank":127.0,"Housing_Affordability_Index_Rank":196.0,"Crime_Rate_Index_Rank":171.0,"Young_Index_Rank":156.0,"Middle_Aged_Index_Rank":132.0,"Old_Index_Rank":89.0}
{"neighbourhood_id":36,"population_density_Rank":79.0,"population_by_gender_Data_Male_Rank":39.0,"population_by_gender_Data_Female_Rank":61.0,"Age_Diversity_Index_Rank":148.0,"Employment_Health_Index_Rank":174.0,"Annual_Earnings_Index_Rank":71.0,"Housing_Affordability_Index_Rank":133.0,"Crime_Rate_Index_Rank":173.0,"Young_Index_Rank":40.0,"Middle_Aged_Index_Rank":56.0,"Old_Index_Rank":30.0}
{"neighbourhood_id":37,"population_density_Rank":103.0,"population_by_gender_Data_Male_Rank":20.0,"population_by_gender_Data_Female_Rank":31.0,"Age_Diversity_Index_Rank":65.0,"Employment_Health_Index_Rank":209.0,"Annual_Earnings_Index_Rank":48.0,"Housing_Affordability_Index_Rank":81.0,"Crime_Rate_Index_Rank":106.0,"Young_Index_Rank":50.0,"Middle_Aged_Index_Rank":22.0,"Old_Index_Rank":5.0}
{"neighbourhood_id":38,"population_density_Rank":103.0,"population_by_gender_Data_Male_Rank":20.0,"population_by_gender_Data_Female_Rank":31.0,"Age_Diversity_Index_Rank":65.0,"Employment_Health_Index_Rank":209.0,"Annual_Earnings_Index_Rank":48.0,"Housing_Affordability_Index_Rank":81.0,"Crime_Rate_Index_Rank":106.0,"Young_Index_Rank":50.0,"Middle_Aged_Index_Rank":22.0,"Old_Index_Rank":5.0}
{"neighbourhood_id":39,"population_density_Rank":47.0,"population_by_gender_Data_Male_Rank":6.0,"population_by_gender_Data_Female_Rank":26.0,"Age_Diversity_Index_Rank":31.0,"Employment_Health_Index_Rank":168.0,"Annual_Earnings_Index_Rank":96.0,"Housing_Affordability_Index_Rank":85.0,"Crime_Rate_Index_Rank":56.0,"Young_Index_Rank":3.0,"Middle_Aged_Index_Rank":61.0,"Old_Index_Rank":45.0}
{"neighbourhood_id":40,"population_density_Rank":47.0,"population_by_gender_Data_Male_Rank":6.0,"population_by_gender_Data_Female_Rank":26.0,"Age_Diversity_Index_Rank":31.0,"Employment_Health_Index_Rank":168.0,"Annual_Earnings_Index_Rank":96.0,"Housing_Affordability_Index_Rank":85.0,"Crime_Rate_Index_Rank":56.0,"Young_Index_Rank":3.0,"Middle_Aged_Index_Rank":61.0,"Old_Index_Rank":45.0}
{"neighbourhood_id":41,"population_density_Rank":66.0,"population_by_gender_Data_Male_Rank":45.0,"population_by_gender_Data_Female_Rank":62.0,"Age_Diversity_Index_Rank":110.0,"Employment_Health_Index_Rank":54.0,"Annual_Earnings_Index_Rank":43.0,"Housing_Affordability_Index_Rank":130.0,"Crime_Rate_Index_Rank":103.0,"Young_Index_Rank":46.0,"Middle_Aged_Index_Rank":52.0,"Old_Index_Rank":78.0}
{"neighbourhood_id":42,"population_density_Rank":81.0,"population_by_gender_Data_Male_Rank":24.0,"population_by_gender_Data_Female_Rank":34.0,"Age_Diversity_Index_Rank":133.0,"Employment_Health_Index_Rank":130.0,"Annual_Earnings_Index_Rank":50.0,"Housing_Affordability_Index_Rank":84.0,"Crime_Rate_Index_Rank":191.0,"Young_Index_Rank":31.0,"Middle_Aged_Index_Rank":41.0,"Old_Index_Rank":11.0}
{"neighbourhood_id":43,"population_density_Rank":134.0,"population_by_gender_Data_Male_Rank":126.0,"population_by_gender_Data_Female_Rank":117.0,"Age_Diversity_Index_Rank":36.0,"Employment_Health_Index_Rank":232.0,"Annual_Earnings_Index_Rank":185.0,"Housing_Affordability_Index_Rank":51.0,"Crime_Rate_Index_Rank":48.0,"Young_Index_Rank":135.0,"Middle_Aged_Index_Rank":123.0,"Old_Index_Rank":22.0}
{"neighbourhood_id":44,"population_density_Rank":134.0,"population_by_gender_Data_Male_Rank":126.0,"population_by_gender_Data_Female_Rank":117.0,"Age_Diversity_Index_Rank":36.0,"Employment_Health_Index_Rank":232.0,"Annual_Earnings_Index_Rank":185.0,"Housing_Affordability_Index_Rank":51.0,"Crime_Rate_Index_Rank":48.0,"Young_Index_Rank":135.0,"Middle_Aged_Index_Rank":123.0,"Old_Index_Rank":22.0}
{"neighbourhood_id":104,"population_density_Rank":156.0,"population_by_gender_Data_Male_Rank":170.0,"population_by_gender_Data_Female_Rank":130.0,"Age_Diversity_Index_Rank":70.0,"Employment_Health_Index_Rank":207.0,"Annual_Earnings_Index_Rank":135.0,"Housing_Affordability_Index_Rank":95.0,"Crime_Rate_Index_Rank":211.0,"Young_Index_Rank":171.0,"Middle_Aged_Index_Rank":135.0,"Old_Index_Rank":53.0}
{"neighbourhood_id":45,"population_density_Rank":122.0,"population_by_gender_Data_Male_Rank":48.0,"population_by_gender_Data_Female_Rank":45.0,"Age_Diversity_Index_Rank":1.0,"Employment_Health_Index_Rank":212.0,"Annual_Earnings_Index_Rank":40.0,"Housing_Affordability_Index_Rank":56.0,"Crime_Rate_Index_Rank":150.0,"Young_Index_Rank":83.0,"Middle_Aged_Index_Rank":29.0,"Old_Index_Rank":1.0}
{"neighbourhood_id":46,"population_density_Rank":134.0,"population_by_gender_Data_Male_Rank":126.0,"population_by_gender_Data_Female_Rank":117.0,"Age_Diversity_Index_Rank":36.0,"Employment_Health_Index_Rank":232.0,"Annual_Earnings_Index_Rank":185.0,"Housing_Affordability_Index_Rank":51.0,"Crime_Rate_Index_Rank":48.0,"Young_Index_Rank":135.0,"Middle_Aged_Index_Rank":123.0,"Old_Index_Rank":22.0}
{"neighbourhood_id":47,"population_density_Rank":29.0,"population_by_gender_Data_Male_Rank":8.0,"population_by_gender_Data_Female_Rank":1.0,"Age_Diversity_Index_Rank":18.0,"Employment_Health_Index_Rank":86.0,"Annual_Earnings_Index_Rank":24.0,"Housing_Affordability_Index_Rank":58.0,"Crime_Rate_Index_Rank":43.0,"Young_Index_Rank":18.0,"Middle_Aged_Index_Rank":2.0,"Old_Index_Rank":42.0}
{"neighbourhood_id":48,"population_density_Rank":66.0,"population_by_gender_Data_Male_Rank":45.0,"population_by_gender_Data_Female_Rank":62.0,"Age_Diversity_Index_Rank":110.0,"Employment_Health_Index_Rank":54.0,"Annual_Earnings_Index_Rank":43.0,"Housing_Affordability_Index_Rank":130.0,"Crime_Rate_Index_Rank":103.0,"Young_Index_Rank":46.0,"Middle_Aged_Index_Rank":52.0,"Old_Index_Rank":78.0}
{"neighbourhood_id":49,"population_density_Rank":109.0,"population_by_gender_Data_Male_Rank":81.0,"population_by_gender_Data_Female_Rank":82.0,"Age_Diversity_Index_Rank":101.0,"Employment_Health_Index_Rank":116.0,"Annual_Earnings_Index_Rank":65.0,"Housing_Affordability_Index_Rank":136.0,"Crime_Rate_Index_Rank":93.0,"Young_Index_Rank":74.0,"Middle_Aged_Index_Rank":88.0,"Old_Index_Rank":98.0}
{"neighbourhood_id":50,"population_density_Rank":108.0,"population_by_gender_Data_Male_Rank":43.0,"population_by_gender_Data_Female_Rank":51.0,"Age_Diversity_Index_Rank":108.0,"Employment_Health_Index_Rank":223.0,"Annual_Earnings_Index_Rank":77.0,"Housing_Affordability_Index_Rank":75.0,"Crime_Rate_Index_Rank":102.0,"Young_Index_Rank":53.0,"Middle_Aged_Index_Rank":45.0,"Old_Index_Rank":17.0}
{"neighbourhood_id":51,"population_density_Rank":113.0,"population_by_gender_Data_Male_Rank":44.0,"population_by_gender_Data_Female_Rank":43.0,"Age_Diversity_Index_Rank":55.0,"Employment_Health_Index_Rank":175.0,"Annual_Earnings_Index_Rank":30.0,"Housing_Affordability_Index_Rank":64.0,"Crime_Rate_Index_Rank":142.0,"Young_Index_Rank":64.0,"Middle_Aged_Index_Rank":33.0,"Old_Index_Rank":7.0}
{"neighbourhood_id":52,"population_density_Rank":122.0,"population_by_gender_Data_Male_Rank":48.0,"population_by_gender_Data_Female_Rank":45.0,"Age_Diversity_Index_Rank":1.0,"Employment_Health_Index_Rank":212.0,"Annual_Earnings_Index_Rank":40.0,"Housing_Affordability_Index_Rank":56.0,"Crime_Rate_Index_Rank":150.0,"Young_Index_Rank":83.0,"Middle_Aged_Index_Rank":29.0,"Old_Index_Rank":1.0}
{"neighbourhood_id":53,"population_density_Rank":76.0,"population_by_gender_Data_Male_Rank":77.0,"population_by_gender_Data_Female_Rank":69.0,"Age_Diversity_Index_Rank":76.0,"Employment_Health_Index_Rank":199.0,"Annual_Earnings_Index_Rank":82.0,"Housing_Affordability_Index_Rank":39.0,"Crime_Rate_Index_Rank":13.0,"Young_Index_Rank":57.0,"Middle_Aged_Index_Rank":77.0,"Old_Index_Rank":116.0}
{"neighbourhood_id":54,"population_density_Rank":61.0,"population_by_gender_Data_Male_Rank":50.0,"population_by_gender_Data_Female_Rank":18.0,"Age_Diversity_Index_Rank":34.0,"Employment_Health_Index_Rank":224.0,"Annual_Earnings_Index_Rank":91.0,"Housing_Affordability_Index_Rank":6.0,"Crime_Rate_Index_Rank":30.0,"Young_Index_Rank":25.0,"Middle_Aged_Index_Rank":34.0,"Old_Index_Rank":59.0}
{"neighbourhood_id":55,"population_density_Rank":29.0,"population_by_gender_Data_Male_Rank":8.0,"population_by_gender_Data_Female_Rank":1.0,"Age_Diversity_Index_Rank":18.0,"Employment_Health_Index_Rank":86.0,"Annual_Earnings_Index_Rank":24.0,"Housing_Affordability_Index_Rank":58.0,"Crime_Rate_Index_Rank":43.0,"Young_Index_Rank":18.0,"Middle_Aged_Index_Rank":2.0,"Old_Index_Rank":42.0}
{"neighbourhood_id":56,"population_density_Rank":118.0,"population_by_gender_Data_Male_Rank":63.0,"population_by_gender_Data_Female_Rank":41.0,"Age_Diversity_Index_Rank":56.0,"Employment_Health_Index_Rank":149.0,"Annual_Earnings_Index_Rank":38.0,"Housing_Affordability_Index_Rank":124.0,"Crime_Rate_Index_Rank":97.0,"Young_Index_Rank":65.0,"Middle_Aged_Index_Rank":36.0,"Old_Index_Rank":20.0}
{"neighbourhood_id":57,"population_density_Rank":118.0,"population_by_gender_Data_Male_Rank":63.0,"population_by_gender_Data_Female_Rank":41.0,"Age_Diversity_Index_Rank":56.0,"Employment_Health_Index_Rank":149.0,"Annual_Earnings_Index_Rank":38.0,"Housing_Affordability_Index_Rank":124.0,"Crime_Rate_Index_Rank":97.0,"Young_Index_Rank":65.0,"Middle_Aged_Index_Rank":36.0,"Old_Index_Rank":20.0}
{"neighbourhood_id":58,"population_density_Rank":61.0,"population_by_gender_Data_Male_Rank":50.0,"population_by_gender_Data_Female_Rank":18.0,"Age_Diversity_Index_Rank":34.0,"Employment_Health_Index_Rank":224.0,"Annual_Earnings_Index_Rank":91.0,"Housing_Affordability_Index_Rank":6.0,"Crime_Rate_Index_Rank":30.0,"Young_Index_Rank":25.0,"Middle_Aged_Index_Rank":34.0,"Old_Index_Rank":59.0}
{"neighbourhood_id":60,"population_density_Rank":109.0,"population_by_gender_Data_Male_Rank":81.0,"population_by_gender_Data_Female_Rank":82.0,"Age_Diversity_Index_Rank":101.0,"Employment_Health_Index_Rank":116.0,"Annual_Earnings_Index_Rank":65.0,"Housing_Affordability_Index_Rank":136.0,"Crime_Rate_Index_Rank":93.0,"Young_Index_Rank":74.0,"Middle_Aged_Index_Rank":88.0,"Old_Index_Rank":98.0}
{"neighbourhood_id":61,"population_density_Rank":205.0,"population_by_gender_Data_Male_Rank":33.0,"population_by_gender_Data_Female_Rank":20.0,"Age_Diversity_Index_Rank":48.0,"Employment_Health_Index_Rank":72.0,"Annual_Earnings_Index_Rank":2.0,"Housing_Affordability_Index_Rank":142.0,"Crime_Rate_Index_Rank":152.0,"Young_Index_Rank":41.0,"Middle_Aged_Index_Rank":14.0,"Old_Index_Rank":13.0}
{"neighbourhood_id":62,"population_density_Rank":150.0,"population_by_gender_Data_Male_Rank":27.0,"population_by_gender_Data_Female_Rank":4.0,"Age_Diversity_Index_Rank":14.0,"Employment_Health_Index_Rank":67.0,"Annual_Earnings_Index_Rank":6.0,"Housing_Affordability_Index_Rank":78.0,"Crime_Rate_Index_Rank":46.0,"Young_Index_Rank":29.0,"Middle_Aged_Index_Rank":8.0,"Old_Index_Rank":33.0}
{"neighbourhood_id":63,"population_density_Rank":205.0,"population_by_gender_Data_Male_Rank":33.0,"population_by_gender_Data_Female_Rank":20.0,"Age_Diversity_Index_Rank":48.0,"Employment_Health_Index_Rank":72.0,"Annual_Earnings_Index_Rank":2.0,"Housing_Affordability_Index_Rank":142.0,"Crime_Rate_Index_Rank":152.0,"Young_Index_Rank":41.0,"Middle_Aged_Index_Rank":14.0,"Old_Index_Rank":13.0}
{"neighbourhood_id":64,"population_density_Rank":205.0,"population_by_gender_Data_Male_Rank":33.0,"population_by_gender_Data_Female_Rank":20.0,"Age_Diversity_Index_Rank":48.0,"Employment_Health_Index_Rank":72.0,"Annual_Earnings_Index_Rank":2.0,"Housing_Affordability_Index_Rank":142.0,"Crime_Rate_Index_Rank":152.0,"Young_Index_Rank":41.0,"Middle_Aged_Index_Rank":14.0,"Old_Index_Rank":13.0}
{"neighbourhood_id":65,"population_density_Rank":150.0,"population_by_gender_Data_Male_Rank":27.0,"population_by_gender_Data_Female_Rank":4.0,"Age_Diversity_Index_Rank":14.0,"Employment_Health_Index_Rank":67.0,"Annual_Earnings_Index_Rank":6.0,"Housing_Affordability_Index_Rank":78.0,"Crime_Rate_Index_Rank":46.0,"Young_Index_Rank":29.0,"Middle_Aged_Index_Rank":8.0,"Old_Index_Rank":33.0}
{"neighbourhood_id":66,"population_density_Rank":29.0,"population_by_gender_Data_Male_Rank":8.0,"population_by_gender_Data_Female_Rank":1.0,"Age_Diversity_Index_Rank":18.0,"Employment_Health_Index_Rank":86.0,"Annual_Earnings_Index_Rank":24.0,"Housing_Affordability_Index_Rank":58.0,"Crime_Rate_Index_Rank":43.0,"Young_Index_Rank":18.0,"Middle_Aged_Index_Rank":2.0,"Old_Index_Rank":42.0}
{"neighbourhood_id":67,"population_density_Rank":205.0,"population_by_gender_Data_Male_Rank":33.0,"population_by_gender_Data_Female_Rank":20.0,"Age_Diversity_Index_Rank":48.0,"Employment_Health_Index_Rank":72.0,"Annual_Earnings_Index_Rank":2.0,"Housing_Affordability_Index_Rank":142.0,"Crime_Rate_Index_Rank":152.0,"Young_Index_Rank":41.0,"Middle_Aged_Index_Rank":14.0,"Old_Index_Rank":13.0}
{"neighbourhood_id":68,"population_density_Rank":191.0,"population_by_gender_Data_Male_Rank":213.0,"population_by_gender_Data_Female_Rank":213.0,"Age_Diversity_Index_Rank":194.0,"Employment_Health_Index_Rank":159.0,"Annual_Earnings_Index_Rank":200.0,"Housing_Affordability_Index_Rank":190.0,"Crime_Rate_Index_Rank":232.0,"Young_Index_Rank":216.0,"Middle_Aged_Index_Rank":210.0,"Old_Index_Rank":184.0}
{"neighbourhood_id":69,"population_density_Rank":158.0,"population_by_gender_Data_Male_Rank":227.0,"population_by_gender_Data_Female_Rank":221.0,"Age_Diversity_Index_Rank":192.0,"Employment_Health_Index_Rank":235.0,"Annual_Earnings_Index_Rank":227.0,"Housing_Affordability_Index_Rank":119.0,"Crime_Rate_Index_Rank":143.0,"Young_Index_Rank":226.0,"Middle_Aged_Index_Rank":225.0,"Old_Index_Rank":189.0}
{"neighbourhood_id":70,"population_density_Rank":117.0,"population_by_gender_Data_Male_Rank":168.0,"population_by_gender_Data_Female_Rank":160.0,"Age_Diversity_Index_Rank":147.0,"Employment_Health_Index_Rank":214.0,"Annual_Earnings_Index_Rank":220.0,"Housing_Affordability_Index_Rank":20.0,"Crime_Rate_Index_Rank":7.0,"Young_Index_Rank":119.0,"Middle_Aged_Index_Rank":186.0,"Old_Index_Rank":195.0}
{"neighbourhood_id":71,"population_density_Rank":58.0,"population_by_gender_Data_Male_Rank":155.0,"population_by_gender_Data_Female_Rank":148.0,"Age_Diversity_Index_Rank":142.0,"Employment_Health_Index_Rank":221.0,"Annual_Earnings_Index_Rank":215.0,"Housing_Affordability_Index_Rank":21.0,"Crime_Rate_Index_Rank":27.0,"Young_Index_Rank":113.0,"Middle_Aged_Index_Rank":176.0,"Old_Index_Rank":193.0}
{"neighbourhood_id":72,"population_density_Rank":225.0,"population_by_gender_Data_Male_Rank":224.0,"population_by_gender_Data_Female_Rank":227.0,"Age_Diversity_Index_Rank":224.0,"Employment_Health_Index_Rank":205.0,"Annual_Earnings_Index_Rank":232.0,"Housing_Affordability_Index_Rank":182.0,"Crime_Rate_Index_Rank":147.0,"Young_Index_Rank":218.0,"Middle_Aged_Index_Rank":227.0,"Old_Index_Rank":230.0}
{"neighbourhood_id":73,"population_density_Rank":54.0,"population_by_gender_Data_Male_Rank":122.0,"population_by_gender_Data_Female_Rank":125.0,"Age_Diversity_Index_Rank":104.0,"Employment_Health_Index_Rank":218.0,"Annual_Earnings_Index_Rank":204.0,"Housing_Affordability_Index_Rank":42.0,"Crime_Rate_Index_Rank":35.0,"Young_Index_Rank":87.0,"Middle_Aged_Index_Rank":146.0,"Old_Index_Rank":174.0}
{"neighbourhood_id":74,"population_density_Rank":58.0,"population_by_gender_Data_Male_Rank":155.0,"population_by_gender_Data_Female_Rank":148.0,"Age_Diversity_Index_Rank":142.0,"Employment_Health_Index_Rank":221.0,"Annual_Earnings_Index_Rank":215.0,"Housing_Affordability_Index_Rank":21.0,"Crime_Rate_Index_Rank":27.0,"Young_Index_Rank":113.0,"Middle_Aged_Index_Rank":176.0,"Old_Index_Rank":193.0}
{"neighbourhood_id":75,"population_density_Rank":21.0,"population_by_gender_Data_Male_Rank":31.0,"population_by_gender_Data_Female_Rank":24.0,"Age_Diversity_Index_Rank":9.0,"Employment_Health_Index_Rank":201.0,"Annual_Earnings_Index_Rank":146.0,"Housing_Affordability_Index_Rank":1.0,"Crime_Rate_Index_Rank":3.0,"Young_Index_Rank":14.0,"Middle_Aged_Index_Rank":38.0,"Old_Index_Rank":100.0}
{"neighbourhood_id":76,"population_density_Rank":21.0,"population_by_gender_Data_Male_Rank":31.0,"population_by_gender_Data_Female_Rank":24.0,"Age_Diversity_Index_Rank":9.0,"Employment_Health_Index_Rank":201.0,"Annual_Earnings_Index_Rank":146.0,"Housing_Affordability_Index_Rank":1.0,"Crime_Rate_Index_Rank":3.0,"Young_Index_Rank":14.0,"Middle_Aged_Index_Rank":38.0,"Old_Index_Rank":100.0}
{"neighbourhood_id":77,"population_density_Rank":54.0,"population_by_gender_Data_Male_Rank":122.0,"population_by_gender_Data_Female_Rank":125.0,"Age_Diversity_Index_Rank":104.0,"Employment_Health_Index_Rank":218.0,"Annual_Earnings_Index_Rank":204.0,"Housing_Affordability_Index_Rank":42.0,"Crime_Rate_Index_Rank":35.0,"Young_Index_Rank":87.0,"Middle_Aged_Index_Rank":146.0,"Old_Index_Rank":174.0}
{"neighbourhood_id":78,"population_density_Rank":54.0,"population_by_gender_Data_Male_Rank":122.0,"population_by_gender_Data_Female_Rank":125.0,"Age_Diversity_Index_Rank":104.0,"Employment_Health_Index_Rank":218.0,"Annual_Earnings_Index_Rank":204.0,"Housing_Affordability_Index_Rank":42.0,"Crime_Rate_Index_Rank":35.0,"Young_Index_Rank":87.0,"Middle_Aged_Index_Rank":146.0,"Old_Index_Rank":174.0}
{"neighbourhood_id":79,"population_density_Rank":85.0,"population_by_gender_Data_Male_Rank":129.0,"population_by_gender_Data_Female_Rank":124.0,"Age_Diversity_Index_Rank":167.0,"Employment_Health_Index_Rank":196.0,"Annual_Earnings_Index_Rank":196.0,"Housing_Affordability_Index_Rank":19.0,"Crime_Rate_Index_Rank":38.0,"Young_Index_Rank":108.0,"Middle_Aged_Index_Rank":145.0,"Old_Index_Rank":135.0}
{"neighbourhood_id":80,"population_density_Rank":32.0,"population_by_gender_Data_Male_Rank":56.0,"population_by_gender_Data_Female_Rank":58.0,"Age_Diversity_Index_Rank":21.0,"Employment_Health_Index_Rank":146.0,"Annual_Earnings_Index_Rank":157.0,"Housing_Affordability_Index_Rank":23.0,"Crime_Rate_Index_Rank":14.0,"Young_Index_Rank":32.0,"Middle_Aged_Index_Rank":63.0,"Old_Index_Rank":149.0}
{"neighbourhood_id":81,"population_density_Rank":32.0,"population_by_gender_Data_Male_Rank":56.0,"population_by_gender_Data_Female_Rank":58.0,"Age_Diversity_Index_Rank":21.0,"Employment_Health_Index_Rank":146.0,"Annual_Earnings_Index_Rank":157.0,"Housing_Affordability_Index_Rank":23.0,"Crime_Rate_Index_Rank":14.0,"Young_Index_Rank":32.0,"Middle_Aged_Index_Rank":63.0,"Old_Index_Rank":149.0}
{"neighbourhood_id":82,"population_density_Rank":65.0,"population_by_gender_Data_Male_Rank":209.0,"population_by_gender_Data_Female_Rank":199.0,"Age_Diversity_Index_Rank":223.0,"Employment_Health_Index_Rank":138.0,"Annual_Earnings_Index_Rank":214.0,"Housing_Affordability_Index_Rank":80.0,"Crime_Rate_Index_Rank":118.0,"Young_Index_Rank":193.0,"Middle_Aged_Index_Rank":209.0,"Old_Index_Rank":207.0}
{"neighbourhood_id":83,"population_density_Rank":32.0,"population_by_gender_Data_Male_Rank":56.0,"population_by_gender_Data_Female_Rank":58.0,"Age_Diversity_Index_Rank":21.0,"Employment_Health_Index_Rank":146.0,"Annual_Earnings_Index_Rank":157.0,"Housing_Affordability_Index_Rank":23.0,"Crime_Rate_Index_Rank":14.0,"Young_Index_Rank":32.0,"Middle_Aged_Index_Rank":63.0,"Old_Index_Rank":149.0}
{"neighbourhood_id":84,"population_density_Rank":20.0,"population_by_gender_Data_Male_Rank":52.0,"population_by_gender_Data_Female_Rank":44.0,"Age_Diversity_Index_Rank":8.0,"Employment_Health_Index_Rank":137.0,"Annual_Earnings_Index_Rank":152.0,"Housing_Affordability_Index_Rank":14.0,"Crime_Rate_Index_Rank":42.0,"Young_Index_Rank":27.0,"Middle_Aged_Index_Rank":55.0,"Old_Index_Rank":152.0}
{"neighbourhood_id":85,"population_density_Rank":42.0,"population_by_gender_Data_Male_Rank":68.0,"population_by_gender_Data_Female_Rank":65.0,"Age_Diversity_Index_Rank":43.0,"Employment_Health_Index_Rank":197.0,"Annual_Earnings_Index_Rank":176.0,"Housing_Affordability_Index_Rank":30.0,"Crime_Rate_Index_Rank":1.0,"Young_Index_Rank":38.0,"Middle_Aged_Index_Rank":78.0,"Old_Index_Rank":139.0}
{"neighbourhood_id":86,"population_density_Rank":26.0,"population_by_gender_Data_Male_Rank":40.0,"population_by_gender_Data_Female_Rank":48.0,"Age_Diversity_Index_Rank":11.0,"Employment_Health_Index_Rank":133.0,"Annual_Earnings_Index_Rank":137.0,"Housing_Affordability_Index_Rank":36.0,"Crime_Rate_Index_Rank":39.0,"Young_Index_Rank":21.0,"Middle_Aged_Index_Rank":67.0,"Old_Index_Rank":143.0}
{"neighbourhood_id":87,"population_density_Rank":87.0,"population_by_gender_Data_Male_Rank":97.0,"population_by_gender_Data_Female_Rank":97.0,"Age_Diversity_Index_Rank":74.0,"Employment_Health_Index_Rank":211.0,"Annual_Earnings_Index_Rank":188.0,"Housing_Affordability_Index_Rank":13.0,"Crime_Rate_Index_Rank":114.0,"Young_Index_Rank":67.0,"Middle_Aged_Index_Rank":119.0,"Old_Index_Rank":155.0}
{"neighbourhood_id":88,"population_density_Rank":42.0,"population_by_gender_Data_Male_Rank":68.0,"population_by_gender_Data_Female_Rank":65.0,"Age_Diversity_Index_Rank":43.0,"Employment_Health_Index_Rank":197.0,"Annual_Earnings_Index_Rank":176.0,"Housing_Affordability_Index_Rank":30.0,"Crime_Rate_Index_Rank":1.0,"Young_Index_Rank":38.0,"Middle_Aged_Index_Rank":78.0,"Old_Index_Rank":139.0}
{"neighbourhood_id":89,"population_density_Rank":26.0,"population_by_gender_Data_Male_Rank":40.0,"population_by_gender_Data_Female_Rank":48.0,"Age_Diversity_Index_Rank":11.0,"Employment_Health_Index_Rank":133.0,"Annual_Earnings_Index_Rank":137.0,"Housing_Affordability_Index_Rank":36.0,"Crime_Rate_Index_Rank":39.0,"Young_Index_Rank":21.0,"Middle_Aged_Index_Rank":67.0,"Old_Index_Rank":143.0}
{"neighbourhood_id":90,"population_density_Rank":37.0,"population_by_gender_Data_Male_Rank":53.0,"population_by_gender_Data_Female_Rank":55.0,"Age_Diversity_Index_Rank":67.0,"Employment_Health_Index_Rank":95.0,"Annual_Earnings_Index_Rank":115.0,"Housing_Affordability_Index_Rank":65.0,"Crime_Rate_Index_Rank":77.0,"Young_Index_Rank":35.0,"Middle_Aged_Index_Rank":58.0,"Old_Index_Rank":102.0}
{"neighbourhood_id":91,"population_density_Rank":37.0,"population_by_gender_Data_Male_Rank":53.0,"population_by_gender_Data_Female_Rank":55.0,"Age_Diversity_Index_Rank":67.0,"Employment_Health_Index_Rank":95.0,"Annual_Earnings_Index_Rank":115.0,"Housing_Affordability_Index_Rank":65.0,"Crime_Rate_Index_Rank":77.0,"Young_Index_Rank":35.0,"Middle_Aged_Index_Rank":58.0,"Old_Index_Rank":102.0}
{"neighbourhood_id":92,"population_density_Rank":95.0,"population_by_gender_Data_Male_Rank":11.0,"population_by_gender_Data_Female_Rank":6.0,"Age_Diversity_Index_Rank":63.0,"Employment_Health_Index_Rank":161.0,"Annual_Earnings_Index_Rank":31.0,"Housing_Affordability_Index_Rank":40.0,"Crime_Rate_Index_Rank":33.0,"Young_Index_Rank":16.0,"Middle_Aged_Index_Rank":18.0,"Old_Index_Rank":40.0}
{"neighbourhood_id":93,"population_density_Rank":37.0,"population_by_gender_Data_Male_Rank":53.0,"population_by_gender_Data_Female_Rank":55.0,"Age_Diversity_Index_Rank":67.0,"Employment_Health_Index_Rank":95.0,"Annual_Earnings_Index_Rank":115.0,"Housing_Affordability_Index_Rank":65.0,"Crime_Rate_Index_Rank":77.0,"Young_Index_Rank":35.0,"Middle_Aged_Index_Rank":58.0,"Old_Index_Rank":102.0}
{"neighbourhood_id":94,"population_density_Rank":80.0,"population_by_gender_Data_Male_Rank":72.0,"population_by_gender_Data_Female_Rank":68.0,"Age_Diversity_Index_Rank":84.0,"Employment_Health_Index_Rank":85.0,"Annual_Earnings_Index_Rank":42.0,"Housing_Affordability_Index_Rank":83.0,"Crime_Rate_Index_Rank":109.0,"Young_Index_Rank":82.0,"Middle_Aged_Index_Rank":74.0,"Old_Index_Rank":12.0}
{"neighbourhood_id":95,"population_density_Rank":222.0,"population_by_gender_Data_Male_Rank":210.0,"population_by_gender_Data_Female_Rank":204.0,"Age_Diversity_Index_Rank":119.0,"Employment_Health_Index_Rank":104.0,"Annual_Earnings_Index_Rank":194.0,"Housing_Affordability_Index_Rank":194.0,"Crime_Rate_Index_Rank":215.0,"Young_Index_Rank":214.0,"Middle_Aged_Index_Rank":212.0,"Old_Index_Rank":123.0}
{"neighbourhood_id":96,"population_density_Rank":46.0,"population_by_gender_Data_Male_Rank":70.0,"population_by_gender_Data_Female_Rank":77.0,"Age_Diversity_Index_Rank":93.0,"Employment_Health_Index_Rank":186.0,"Annual_Earnings_Index_Rank":163.0,"Housing_Affordability_Index_Rank":45.0,"Crime_Rate_Index_Rank":29.0,"Young_Index_Rank":52.0,"Middle_Aged_Index_Rank":90.0,"Old_Index_Rank":115.0}
{"neighbourhood_id":97,"population_density_Rank":147.0,"population_by_gender_Data_Male_Rank":100.0,"population_by_gender_Data_Female_Rank":89.0,"Age_Diversity_Index_Rank":96.0,"Employment_Health_Index_Rank":215.0,"Annual_Earnings_Index_Rank":129.0,"Housing_Affordability_Index_Rank":26.0,"Crime_Rate_Index_Rank":110.0,"Young_Index_Rank":77.0,"Middle_Aged_Index_Rank":100.0,"Old_Index_Rank":91.0}
{"neighbourhood_id":98,"population_density_Rank":147.0,"population_by_gender_Data_Male_Rank":100.0,"population_by_gender_Data_Female_Rank":89.0,"Age_Diversity_Index_Rank":96.0,"Employment_Health_Index_Rank":215.0,"Annual_Earnings_Index_Rank":129.0,"Housing_Affordability_Index_Rank":26.0,"Crime_Rate_Index_Rank":110.0,"Young_Index_Rank":77.0,"Middle_Aged_Index_Rank":100.0,"Old_Index_Rank":91.0}
{"neighbourhood_id":99,"population_density_Rank":70.0,"population_by_gender_Data_Male_Rank":59.0,"population_by_gender_Data_Female_Rank":52.0,"Age_Diversity_Index_Rank":90.0,"Employment_Health_Index_Rank":127.0,"Annual_Earnings_Index_Rank":34.0,"Housing_Affordability_Index_Rank":105.0,"Crime_Rate_Index_Rank":137.0,"Young_Index_Rank":54.0,"Middle_Aged_Index_Rank":42.0,"Old_Index_Rank":63.0}
{"neighbourhood_id":100,"population_density_Rank":147.0,"population_by_gender_Data_Male_Rank":100.0,"population_by_gender_Data_Female_Rank":89.0,"Age_Diversity_Index_Rank":96.0,"Employment_Health_Index_Rank":215.0,"Annual_Earnings_Index_Rank":129.0,"Housing_Affordability_Index_Rank":26.0,"Crime_Rate_Index_Rank":110.0,"Young_Index_Rank":77.0,"Middle_Aged_Index_Rank":100.0,"Old_Index_Rank":91.0}
{"neighbourhood_id":101,"population_density_Rank":70.0,"population_by_gender_Data_Male_Rank":59.0,"population_by_gender_Data_Female_Rank":52.0,"Age_Diversity_Index_Rank":90.0,"Employment_Health_Index_Rank":127.0,"Annual_Earnings_Index_Rank":34.0,"Housing_Affordability_Index_Rank":105.0,"Crime_Rate_Index_Rank":137.0,"Young_Index_Rank":54.0,"Middle_Aged_Index_Rank":42.0,"Old_Index_Rank":63.0}
{"neighbourhood_id":102,"population_density_Rank":203.0,"population_by_gender_Data_Male_Rank":137.0,"population_by_gender_Data_Female_Rank":136.0,"Age_Diversity_Index_Rank":163.0,"Employment_Health_Index_Rank":143.0,"Annual_Earnings_Index_Rank":90.0,"Housing_Affordability_Index_Rank":155.0,"Crime_Rate_Index_Rank":71.0,"Young_Index_Rank":144.0,"Middle_Aged_Index_Rank":137.0,"Old_Index_Rank":94.0}
{"neighbourhood_id":103,"population_density_Rank":173.0,"population_by_gender_Data_Male_Rank":117.0,"population_by_gender_Data_Female_Rank":120.0,"Age_Diversity_Index_Rank":177.0,"Employment_Health_Index_Rank":139.0,"Annual_Earnings_Index_Rank":84.0,"Housing_Affordability_Index_Rank":158.0,"Crime_Rate_Index_Rank":83.0,"Young_Index_Rank":121.0,"Middle_Aged_Index_Rank":116.0,"Old_Index_Rank":68.0}
{"neighbourhood_id":105,"population_density_Rank":235.0,"population_by_gender_Data_Male_Rank":231.0,"population_by_gender_Data_Female_Rank":231.0,"Age_Diversity_Index_Rank":233.0,"Employment_Health_Index_Rank":91.0,"Annual_Earnings_Index_Rank":230.0,"Housing_Affordability_Index_Rank":232.0,"Crime_Rate_Index_Rank":230.0,"Young_Index_Rank":231.0,"Middle_Aged_Index_Rank":231.0,"Old_Index_Rank":228.0}
{"neighbourhood_id":107,"population_density_Rank":70.0,"population_by_gender_Data_Male_Rank":59.0,"population_by_gender_Data_Female_Rank":52.0,"Age_Diversity_Index_Rank":90.0,"Employment_Health_Index_Rank":127.0,"Annual_Earnings_Index_Rank":34.0,"Housing_Affordability_Index_Rank":105.0,"Crime_Rate_Index_Rank":137.0,"Young_Index_Rank":54.0,"Middle_Aged_Index_Rank":42.0,"Old_Index_Rank":63.0}
{"neighbourhood_id":108,"population_density_Rank":173.0,"population_by_gender_Data_Male_Rank":117.0,"population_by_gender_Data_Female_Rank":120.0,"Age_Diversity_Index_Rank":177.0,"Employment_Health_Index_Rank":139.0,"Annual_Earnings_Index_Rank":84.0,"Housing_Affordability_Index_Rank":158.0,"Crime_Rate_Index_Rank":83.0,"Young_Index_Rank":121.0,"Middle_Aged_Index_Rank":116.0,"Old_Index_Rank":68.0}
{"neighbourhood_id":109,"population_density_Rank":146.0,"population_by_gender_Data_Male_Rank":74.0,"population_by_gender_Data_Female_Rank":71.0,"Age_Diversity_Index_Rank":109.0,"Employment_Health_Index_Rank":165.0,"Annual_Earnings_Index_Rank":51.0,"Housing_Affordability_Index_Rank":111.0,"Crime_Rate_Index_Rank":162.0,"Young_Index_Rank":76.0,"Middle_Aged_Index_Rank":76.0,"Old_Index_Rank":38.0}
{"neighbourhood_id":110,"population_density_Rank":95.0,"population_by_gender_Data_Male_Rank":11.0,"population_by_gender_Data_Female_Rank":6.0,"Age_Diversity_Index_Rank":63.0,"Employment_Health_Index_Rank":161.0,"Annual_Earnings_Index_Rank":31.0,"Housing_Affordability_Index_Rank":40.0,"Crime_Rate_Index_Rank":33.0,"Young_Index_Rank":16.0,"Middle_Aged_Index_Rank":18.0,"Old_Index_Rank":40.0}
{"neighbourhood_id":111,"population_density_Rank":173.0,"population_by_gender_Data_Male_Rank":117.0,"population_by_gender_Data_Female_Rank":120.0,"Age_Diversity_Index_Rank":177.0,"Employment_Health_Index_Rank":139.0,"Annual_Earnings_Index_Rank":84.0,"Housing_Affordability_Index_Rank":158.0,"Crime_Rate_Index_Rank":83.0,"Young_Index_Rank":121.0,"Middle_Aged_Index_Rank":116.0,"Old_Index_Rank":68.0}
{"neighbourhood_id":112,"population_density_Rank":215.0,"population_by_gender_Data_Male_Rank":221.0,"population_by_gender_Data_Female_Rank":223.0,"Age_Diversity_Index_Rank":231.0,"Employment_Health_Index_Rank":59.0,"Annual_Earnings_Index_Rank":217.0,"Housing_Affordability_Index_Rank":208.0,"Crime_Rate_Index_Rank":164.0,"Young_Index_Rank":221.0,"Middle_Aged_Index_Rank":221.0,"Old_Index_Rank":216.0}
{"neighbourhood_id":113,"population_density_Rank":156.0,"population_by_gender_Data_Male_Rank":170.0,"population_by_gender_Data_Female_Rank":130.0,"Age_Diversity_Index_Rank":70.0,"Employment_Health_Index_Rank":207.0,"Annual_Earnings_Index_Rank":135.0,"Housing_Affordability_Index_Rank":95.0,"Crime_Rate_Index_Rank":211.0,"Young_Index_Rank":171.0,"Middle_Aged_Index_Rank":135.0,"Old_Index_Rank":53.0}
{"neighbourhood_id":114,"population_density_Rank":131.0,"population_by_gender_Data_Male_Rank":73.0,"population_by_gender_Data_Female_Rank":67.0,"Age_Diversity_Index_Rank":75.0,"Employment_Health_Index_Rank":120.0,"Annual_Earnings_Index_Rank":64.0,"Housing_Affordability_Index_Rank":68.0,"Crime_Rate_Index_Rank":53.0,"Young_Index_Rank":60.0,"Middle_Aged_Index_Rank":75.0,"Old_Index_Rank":84.0}
{"neighbourhood_id":116,"population_density_Rank":222.0,"population_by_gender_Data_Male_Rank":210.0,"population_by_gender_Data_Female_Rank":204.0,"Age_Diversity_Index_Rank":119.0,"Employment_Health_Index_Rank":104.0,"Annual_Earnings_Index_Rank":194.0,"Housing_Affordability_Index_Rank":194.0,"Crime_Rate_Index_Rank":215.0,"Young_Index_Rank":214.0,"Middle_Aged_Index_Rank":212.0,"Old_Index_Rank":123.0}
{"neighbourhood_id":117,"population_density_Rank":26.0,"population_by_gender_Data_Male_Rank":40.0,"population_by_gender_Data_Female_Rank":48.0,"Age_Diversity_Index_Rank":11.0,"Employment_Health_Index_Rank":133.0,"Annual_Earnings_Index_Rank":137.0,"Housing_Affordability_Index_Rank":36.0,"Crime_Rate_Index_Rank":39.0,"Young_Index_Rank":21.0,"Middle_Aged_Index_Rank":67.0,"Old_Index_Rank":143.0}
{"neighbourhood_id":118,"population_density_Rank":235.0,"population_by_gender_Data_Male_Rank":231.0,"population_by_gender_Data_Female_Rank":231.0,"Age_Diversity_Index_Rank":233.0,"Employment_Health_Index_Rank":91.0,"Annual_Earnings_Index_Rank":230.0,"Housing_Affordability_Index_Rank":232.0,"Crime_Rate_Index_Rank":230.0,"Young_Index_Rank":231.0,"Middle_Aged_Index_Rank":231.0,"Old_Index_Rank":228.0}
{"neighbourhood_id":119,"population_density_Rank":10.0,"population_by_gender_Data_Male_Rank":229.0,"population_by_gender_Data_Female_Rank":229.0,"Age_Diversity_Index_Rank":207.0,"Employment_Health_Index_Rank":1.0,"Annual_Earnings_Index_Rank":218.0,"Housing_Affordability_Index_Rank":227.0,"Crime_Rate_Index_Rank":80.0,"Young_Index_Rank":229.0,"Middle_Aged_Index_Rank":229.0,"Old_Index_Rank":235.0}
{"neighbourhood_id":120,"population_density_Rank":74.0,"population_by_gender_Data_Male_Rank":191.0,"population_by_gender_Data_Female_Rank":196.0,"Age_Diversity_Index_Rank":198.0,"Employment_Health_Index_Rank":36.0,"Annual_Earnings_Index_Rank":181.0,"Housing_Affordability_Index_Rank":128.0,"Crime_Rate_Index_Rank":11.0,"Young_Index_Rank":199.0,"Middle_Aged_Index_Rank":187.0,"Old_Index_Rank":191.0}
{"neighbourhood_id":121,"population_density_Rank":233.0,"population_by_gender_Data_Male_Rank":235.0,"population_by_gender_Data_Female_Rank":235.0,"Age_Diversity_Index_Rank":235.0,"Employment_Health_Index_Rank":2.0,"Annual_Earnings_Index_Rank":234.0,"Housing_Affordability_Index_Rank":235.0,"Crime_Rate_Index_Rank":89.0,"Young_Index_Rank":235.0,"Middle_Aged_Index_Rank":235.0,"Old_Index_Rank":234.0}
{"neighbourhood_id":122,"population_density_Rank":74.0,"population_by_gender_Data_Male_Rank":191.0,"population_by_gender_Data_Female_Rank":196.0,"Age_Diversity_Index_Rank":198.0,"Employment_Health_Index_Rank":36.0,"Annual_Earnings_Index_Rank":181.0,"Housing_Affordability_Index_Rank":128.0,"Crime_Rate_Index_Rank":11.0,"Young_Index_Rank":199.0,"Middle_Aged_Index_Rank":187.0,"Old_Index_Rank":191.0}
{"neighbourhood_id":123,"population_density_Rank":35.0,"population_by_gender_Data_Male_Rank":205.0,"population_by_gender_Data_Female_Rank":208.0,"Age_Diversity_Index_Rank":152.0,"Employment_Health_Index_Rank":8.0,"Annual_Earnings_Index_Rank":114.0,"Housing_Affordability_Index_Rank":138.0,"Crime_Rate_Index_Rank":119.0,"Young_Index_Rank":209.0,"Middle_Aged_Index_Rank":206.0,"Old_Index_Rank":203.0}
{"neighbourhood_id":124,"population_density_Rank":57.0,"population_by_gender_Data_Male_Rank":179.0,"population_by_gender_Data_Female_Rank":188.0,"Age_Diversity_Index_Rank":100.0,"Employment_Health_Index_Rank":6.0,"Annual_Earnings_Index_Rank":78.0,"Housing_Affordability_Index_Rank":162.0,"Crime_Rate_Index_Rank":175.0,"Young_Index_Rank":202.0,"Middle_Aged_Index_Rank":166.0,"Old_Index_Rank":183.0}
{"neighbourhood_id":125,"population_density_Rank":12.0,"population_by_gender_Data_Male_Rank":37.0,"population_by_gender_Data_Female_Rank":39.0,"Age_Diversity_Index_Rank":41.0,"Employment_Health_Index_Rank":190.0,"Annual_Earnings_Index_Rank":52.0,"Housing_Affordability_Index_Rank":3.0,"Crime_Rate_Index_Rank":69.0,"Young_Index_Rank":72.0,"Middle_Aged_Index_Rank":31.0,"Old_Index_Rank":3.0}
{"neighbourhood_id":126,"population_density_Rank":12.0,"population_by_gender_Data_Male_Rank":37.0,"population_by_gender_Data_Female_Rank":39.0,"Age_Diversity_Index_Rank":41.0,"Employment_Health_Index_Rank":190.0,"Annual_Earnings_Index_Rank":52.0,"Housing_Affordability_Index_Rank":3.0,"Crime_Rate_Index_Rank":69.0,"Young_Index_Rank":72.0,"Middle_Aged_Index_Rank":31.0,"Old_Index_Rank":3.0}
{"neighbourhood_id":127,"population_density_Rank":8.0,"population_by_gender_Data_Male_Rank":83.0,"population_by_gender_Data_Female_Rank":87.0,"Age_Diversity_Index_Rank":58.0,"Employment_Health_Index_Rank":39.0,"Annual_Earnings_Index_Rank":18.0,"Housing_Affordability_Index_Rank":17.0,"Crime_Rate_Index_Rank":157.0,"Young_Index_Rank":95.0,"Middle_Aged_Index_Rank":81.0,"Old_Index_Rank":66.0}
{"neighbourhood_id":128,"population_density_Rank":130.0,"population_by_gender_Data_Male_Rank":212.0,"population_by_gender_Data_Female_Rank":212.0,"Age_Diversity_Index_Rank":201.0,"Employment_Health_Index_Rank":11.0,"Annual_Earnings_Index_Rank":183.0,"Housing_Affordability_Index_Rank":157.0,"Crime_Rate_Index_Rank":169.0,"Young_Index_Rank":212.0,"Middle_Aged_Index_Rank":214.0,"Old_Index_Rank":209.0}
{"neighbourhood_id":129,"population_density_Rank":187.0,"population_by_gender_Data_Male_Rank":230.0,"population_by_gender_Data_Female_Rank":230.0,"Age_Diversity_Index_Rank":229.0,"Employment_Health_Index_Rank":4.0,"Annual_Earnings_Index_Rank":225.0,"Housing_Affordability_Index_Rank":218.0,"Crime_Rate_Index_Rank":17.0,"Young_Index_Rank":230.0,"Middle_Aged_Index_Rank":230.0,"Old_Index_Rank":232.0}
{"neighbourhood_id":131,"population_density_Rank":97.0,"population_by_gender_Data_Male_Rank":110.0,"population_by_gender_Data_Female_Rank":107.0,"Age_Diversity_Index_Rank":187.0,"Employment_Health_Index_Rank":121.0,"Annual_Earnings_Index_Rank":100.0,"Housing_Affordability_Index_Rank":87.0,"Crime_Rate_Index_Rank":82.0,"Young_Index_Rank":102.0,"Middle_Aged_Index_Rank":111.0,"Old_Index_Rank":108.0}
{"neighbourhood_id":132,"population_density_Rank":8.0,"population_by_gender_Data_Male_Rank":83.0,"population_by_gender_Data_Female_Rank":87.0,"Age_Diversity_Index_Rank":58.0,"Employment_Health_Index_Rank":39.0,"Annual_Earnings_Index_Rank":18.0,"Housing_Affordability_Index_Rank":17.0,"Crime_Rate_Index_Rank":157.0,"Young_Index_Rank":95.0,"Middle_Aged_Index_Rank":81.0,"Old_Index_Rank":66.0}
{"neighbourhood_id":133,"population_density_Rank":24.0,"population_by_gender_Data_Male_Rank":186.0,"population_by_gender_Data_Female_Rank":184.0,"Age_Diversity_Index_Rank":113.0,"Employment_Health_Index_Rank":26.0,"Annual_Earnings_Index_Rank":108.0,"Housing_Affordability_Index_Rank":153.0,"Crime_Rate_Index_Rank":63.0,"Young_Index_Rank":181.0,"Middle_Aged_Index_Rank":191.0,"Old_Index_Rank":170.0}
{"neighbourhood_id":134,"population_density_Rank":24.0,"population_by_gender_Data_Male_Rank":186.0,"population_by_gender_Data_Female_Rank":184.0,"Age_Diversity_Index_Rank":113.0,"Employment_Health_Index_Rank":26.0,"Annual_Earnings_Index_Rank":108.0,"Housing_Affordability_Index_Rank":153.0,"Crime_Rate_Index_Rank":63.0,"Young_Index_Rank":181.0,"Middle_Aged_Index_Rank":191.0,"Old_Index_Rank":170.0}
{"neighbourhood_id":135,"population_density_Rank":36.0,"population_by_gender_Data_Male_Rank":188.0,"population_by_gender_Data_Female_Rank":182.0,"Age_Diversity_Index_Rank":72.0,"Employment_Health_Index_Rank":18.0,"Annual_Earnings_Index_Rank":99.0,"Housing_Affordability_Index_Rank":200.0,"Crime_Rate_Index_Rank":188.0,"Young_Index_Rank":213.0,"Middle_Aged_Index_Rank":174.0,"Old_Index_Rank":74.0}
{"neighbourhood_id":136,"population_density_Rank":69.0,"population_by_gender_Data_Male_Rank":220.0,"population_by_gender_Data_Female_Rank":220.0,"Age_Diversity_Index_Rank":186.0,"Employment_Health_Index_Rank":5.0,"Annual_Earnings_Index_Rank":170.0,"Housing_Affordability_Index_Rank":184.0,"Crime_Rate_Index_Rank":217.0,"Young_Index_Rank":228.0,"Middle_Aged_Index_Rank":217.0,"Old_Index_Rank":212.0}
{"neighbourhood_id":137,"population_density_Rank":2.0,"population_by_gender_Data_Male_Rank":87.0,"population_by_gender_Data_Female_Rank":78.0,"Age_Diversity_Index_Rank":45.0,"Employment_Health_Index_Rank":21.0,"Annual_Earnings_Index_Rank":15.0,"Housing_Affordability_Index_Rank":72.0,"Crime_Rate_Index_Rank":176.0,"Young_Index_Rank":127.0,"Middle_Aged_Index_Rank":70.0,"Old_Index_Rank":25.0}
{"neighbourhood_id":138,"population_density_Rank":2.0,"population_by_gender_Data_Male_Rank":87.0,"population_by_gender_Data_Female_Rank":78.0,"Age_Diversity_Index_Rank":45.0,"Employment_Health_Index_Rank":21.0,"Annual_Earnings_Index_Rank":15.0,"Housing_Affordability_Index_Rank":72.0,"Crime_Rate_Index_Rank":176.0,"Young_Index_Rank":127.0,"Middle_Aged_Index_Rank":70.0,"Old_Index_Rank":25.0}
{"neighbourhood_id":139,"population_density_Rank":40.0,"population_by_gender_Data_Male_Rank":92.0,"population_by_gender_Data_Female_Rank":94.0,"Age_Diversity_Index_Rank":53.0,"Employment_Health_Index_Rank":13.0,"Annual_Earnings_Index_Rank":20.0,"Housing_Affordability_Index_Rank":114.0,"Crime_Rate_Index_Rank":92.0,"Young_Index_Rank":132.0,"Middle_Aged_Index_Rank":73.0,"Old_Index_Rank":35.0}
{"neighbourhood_id":140,"population_density_Rank":23.0,"population_by_gender_Data_Male_Rank":189.0,"population_by_gender_Data_Female_Rank":177.0,"Age_Diversity_Index_Rank":107.0,"Employment_Health_Index_Rank":14.0,"Annual_Earnings_Index_Rank":89.0,"Housing_Affordability_Index_Rank":165.0,"Crime_Rate_Index_Rank":198.0,"Young_Index_Rank":204.0,"Middle_Aged_Index_Rank":175.0,"Old_Index_Rank":107.0}
{"neighbourhood_id":141,"population_density_Rank":5.0,"population_by_gender_Data_Male_Rank":151.0,"population_by_gender_Data_Female_Rank":128.0,"Age_Diversity_Index_Rank":62.0,"Employment_Health_Index_Rank":25.0,"Annual_Earnings_Index_Rank":60.0,"Housing_Affordability_Index_Rank":171.0,"Crime_Rate_Index_Rank":183.0,"Young_Index_Rank":184.0,"Middle_Aged_Index_Rank":127.0,"Old_Index_Rank":47.0}
{"neighbourhood_id":142,"population_density_Rank":1.0,"population_by_gender_Data_Male_Rank":138.0,"population_by_gender_Data_Female_Rank":123.0,"Age_Diversity_Index_Rank":89.0,"Employment_Health_Index_Rank":9.0,"Annual_Earnings_Index_Rank":33.0,"Housing_Affordability_Index_Rank":135.0,"Crime_Rate_Index_Rank":184.0,"Young_Index_Rank":166.0,"Middle_Aged_Index_Rank":122.0,"Old_Index_Rank":76.0}
{"neighbourhood_id":143,"population_density_Rank":97.0,"population_by_gender_Data_Male_Rank":110.0,"population_by_gender_Data_Female_Rank":107.0,"Age_Diversity_Index_Rank":187.0,"Employment_Health_Index_Rank":121.0,"Annual_Earnings_Index_Rank":100.0,"Housing_Affordability_Index_Rank":87.0,"Crime_Rate_Index_Rank":146.0,"Young_Index_Rank":102.0,"Middle_Aged_Index_Rank":111.0,"Old_Index_Rank":108.0}
{"neighbourhood_id":144,"population_density_Rank":41.0,"population_by_gender_Data_Male_Rank":91.0,"population_by_gender_Data_Female_Rank":92.0,"Age_Diversity_Index_Rank":73.0,"Employment_Health_Index_Rank":176.0,"Annual_Earnings_Index_Rank":81.0,"Housing_Affordability_Index_Rank":29.0,"Crime_Rate_Index_Rank":67.0,"Young_Index_Rank":71.0,"Middle_Aged_Index_Rank":108.0,"Old_Index_Rank":122.0}
{"neighbourhood_id":145,"population_density_Rank":19.0,"population_by_gender_Data_Male_Rank":90.0,"population_by_gender_Data_Female_Rank":106.0,"Age_Diversity_Index_Rank":131.0,"Employment_Health_Index_Rank":66.0,"Annual_Earnings_Index_Rank":98.0,"Housing_Affordability_Index_Rank":46.0,"Crime_Rate_Index_Rank":145.0,"Young_Index_Rank":90.0,"Middle_Aged_Index_Rank":103.0,"Old_Index_Rank":117.0}
{"neighbourhood_id":146,"population_density_Rank":7.0,"population_by_gender_Data_Male_Rank":178.0,"population_by_gender_Data_Female_Rank":174.0,"Age_Diversity_Index_Rank":172.0,"Employment_Health_Index_Rank":132.0,"Annual_Earnings_Index_Rank":166.0,"Housing_Affordability_Index_Rank":62.0,"Crime_Rate_Index_Rank":81.0,"Young_Index_Rank":167.0,"Middle_Aged_Index_Rank":171.0,"Old_Index_Rank":201.0}
{"neighbourhood_id":147,"population_density_Rank":11.0,"population_by_gender_Data_Male_Rank":199.0,"population_by_gender_Data_Female_Rank":191.0,"Age_Diversity_Index_Rank":206.0,"Employment_Health_Index_Rank":112.0,"Annual_Earnings_Index_Rank":209.0,"Housing_Affordability_Index_Rank":50.0,"Crime_Rate_Index_Rank":90.0,"Young_Index_Rank":185.0,"Middle_Aged_Index_Rank":198.0,"Old_Index_Rank":211.0}
{"neighbourhood_id":148,"population_density_Rank":14.0,"population_by_gender_Data_Male_Rank":62.0,"population_by_gender_Data_Female_Rank":47.0,"Age_Diversity_Index_Rank":137.0,"Employment_Health_Index_Rank":185.0,"Annual_Earnings_Index_Rank":72.0,"Housing_Affordability_Index_Rank":5.0,"Crime_Rate_Index_Rank":68.0,"Young_Index_Rank":49.0,"Middle_Aged_Index_Rank":66.0,"Old_Index_Rank":39.0}
{"neighbourhood_id":149,"population_density_Rank":153.0,"population_by_gender_Data_Male_Rank":174.0,"population_by_gender_Data_Female_Rank":186.0,"Age_Diversity_Index_Rank":210.0,"Employment_Health_Index_Rank":230.0,"Annual_Earnings_Index_Rank":207.0,"Housing_Affordability_Index_Rank":15.0,"Crime_Rate_Index_Rank":122.0,"Young_Index_Rank":160.0,"Middle_Aged_Index_Rank":182.0,"Old_Index_Rank":177.0}
{"neighbourhood_id":150,"population_density_Rank":153.0,"population_by_gender_Data_Male_Rank":174.0,"population_by_gender_Data_Female_Rank":186.0,"Age_Diversity_Index_Rank":210.0,"Employment_Health_Index_Rank":230.0,"Annual_Earnings_Index_Rank":207.0,"Housing_Affordability_Index_Rank":15.0,"Crime_Rate_Index_Rank":122.0,"Young_Index_Rank":160.0,"Middle_Aged_Index_Rank":182.0,"Old_Index_Rank":177.0}
{"neighbourhood_id":151,"population_density_Rank":18.0,"population_by_gender_Data_Male_Rank":86.0,"population_by_gender_Data_Female_Rank":98.0,"Age_Diversity_Index_Rank":138.0,"Employment_Health_Index_Rank":89.0,"Annual_Earnings_Index_Rank":132.0,"Housing_Affordability_Index_Rank":63.0,"Crime_Rate_Index_Rank":113.0,"Young_Index_Rank":91.0,"Middle_Aged_Index_Rank":99.0,"Old_Index_Rank":85.0}
{"neighbourhood_id":152,"population_density_Rank":6.0,"population_by_gender_Data_Male_Rank":142.0,"population_by_gender_Data_Female_Rank":135.0,"Age_Diversity_Index_Rank":216.0,"Employment_Health_Index_Rank":70.0,"Annual_Earnings_Index_Rank":165.0,"Housing_Affordability_Index_Rank":115.0,"Crime_Rate_Index_Rank":165.0,"Young_Index_Rank":142.0,"Middle_Aged_Index_Rank":138.0,"Old_Index_Rank":125.0}
{"neighbourhood_id":153,"population_density_Rank":127.0,"population_by_gender_Data_Male_Rank":159.0,"population_by_gender_Data_Female_Rank":150.0,"Age_Diversity_Index_Rank":169.0,"Employment_Health_Index_Rank":32.0,"Annual_Earnings_Index_Rank":168.0,"Housing_Affordability_Index_Rank":117.0,"Crime_Rate_Index_Rank":95.0,"Young_Index_Rank":152.0,"Middle_Aged_Index_Rank":143.0,"Old_Index_Rank":165.0}
{"neighbourhood_id":154,"population_density_Rank":16.0,"population_by_gender_Data_Male_Rank":98.0,"population_by_gender_Data_Female_Rank":112.0,"Age_Diversity_Index_Rank":141.0,"Employment_Health_Index_Rank":44.0,"Annual_Earnings_Index_Rank":105.0,"Housing_Affordability_Index_Rank":94.0,"Crime_Rate_Index_Rank":72.0,"Young_Index_Rank":101.0,"Middle_Aged_Index_Rank":107.0,"Old_Index_Rank":106.0}
{"neighbourhood_id":155,"population_density_Rank":127.0,"population_by_gender_Data_Male_Rank":159.0,"population_by_gender_Data_Female_Rank":150.0,"Age_Diversity_Index_Rank":169.0,"Employment_Health_Index_Rank":32.0,"Annual_Earnings_Index_Rank":168.0,"Housing_Affordability_Index_Rank":117.0,"Crime_Rate_Index_Rank":95.0,"Young_Index_Rank":152.0,"Middle_Aged_Index_Rank":143.0,"Old_Index_Rank":165.0}
{"neighbourhood_id":156,"population_density_Rank":2.0,"population_by_gender_Data_Male_Rank":87.0,"population_by_gender_Data_Female_Rank":78.0,"Age_Diversity_Index_Rank":45.0,"Employment_Health_Index_Rank":21.0,"Annual_Earnings_Index_Rank":15.0,"Housing_Affordability_Index_Rank":72.0,"Crime_Rate_Index_Rank":176.0,"Young_Index_Rank":127.0,"Middle_Aged_Index_Rank":70.0,"Old_Index_Rank":25.0}
{"neighbourhood_id":157,"population_density_Rank":161.0,"population_by_gender_Data_Male_Rank":166.0,"population_by_gender_Data_Female_Rank":169.0,"Age_Diversity_Index_Rank":155.0,"Employment_Health_Index_Rank":28.0,"Annual_Earnings_Index_Rank":106.0,"Housing_Affordability_Index_Rank":168.0,"Crime_Rate_Index_Rank":196.0,"Young_Index_Rank":174.0,"Middle_Aged_Index_Rank":164.0,"Old_Index_Rank":146.0}
{"neighbourhood_id":158,"population_density_Rank":91.0,"population_by_gender_Data_Male_Rank":173.0,"population_by_gender_Data_Female_Rank":183.0,"Age_Diversity_Index_Rank":171.0,"Employment_Health_Index_Rank":24.0,"Annual_Earnings_Index_Rank":145.0,"Housing_Affordability_Index_Rank":141.0,"Crime_Rate_Index_Rank":180.0,"Young_Index_Rank":168.0,"Middle_Aged_Index_Rank":178.0,"Old_Index_Rank":188.0}
{"neighbourhood_id":159,"population_density_Rank":83.0,"population_by_gender_Data_Male_Rank":149.0,"population_by_gender_Data_Female_Rank":157.0,"Age_Diversity_Index_Rank":164.0,"Employment_Health_Index_Rank":30.0,"Annual_Earnings_Index_Rank":119.0,"Housing_Affordability_Index_Rank":101.0,"Crime_Rate_Index_Rank":128.0,"Young_Index_Rank":162.0,"Middle_Aged_Index_Rank":158.0,"Old_Index_Rank":153.0}
{"neighbourhood_id":160,"population_density_Rank":63.0,"population_by_gender_Data_Male_Rank":140.0,"population_by_gender_Data_Female_Rank":161.0,"Age_Diversity_Index_Rank":117.0,"Employment_Health_Index_Rank":15.0,"Annual_Earnings_Index_Rank":94.0,"Housing_Affordability_Index_Rank":178.0,"Crime_Rate_Index_Rank":73.0,"Young_Index_Rank":158.0,"Middle_Aged_Index_Rank":155.0,"Old_Index_Rank":172.0}
{"neighbourhood_id":161,"population_density_Rank":83.0,"population_by_gender_Data_Male_Rank":149.0,"population_by_gender_Data_Female_Rank":157.0,"Age_Diversity_Index_Rank":164.0,"Employment_Health_Index_Rank":30.0,"Annual_Earnings_Index_Rank":119.0,"Housing_Affordability_Index_Rank":101.0,"Crime_Rate_Index_Rank":128.0,"Young_Index_Rank":162.0,"Middle_Aged_Index_Rank":158.0,"Old_Index_Rank":153.0}
{"neighbourhood_id":162,"population_density_Rank":225.0,"population_by_gender_Data_Male_Rank":224.0,"population_by_gender_Data_Female_Rank":227.0,"Age_Diversity_Index_Rank":224.0,"Employment_Health_Index_Rank":205.0,"Annual_Earnings_Index_Rank":232.0,"Housing_Affordability_Index_Rank":182.0,"Crime_Rate_Index_Rank":147.0,"Young_Index_Rank":218.0,"Middle_Aged_Index_Rank":227.0,"Old_Index_Rank":230.0}
{"neighbourhood_id":163,"population_density_Rank":63.0,"population_by_gender_Data_Male_Rank":140.0,"population_by_gender_Data_Female_Rank":161.0,"Age_Diversity_Index_Rank":117.0,"Employment_Health_Index_Rank":15.0,"Annual_Earnings_Index_Rank":94.0,"Housing_Affordability_Index_Rank":178.0,"Crime_Rate_Index_Rank":73.0,"Young_Index_Rank":158.0,"Middle_Aged_Index_Rank":155.0,"Old_Index_Rank":172.0}
{"neighbourhood_id":165,"population_density_Rank":161.0,"population_by_gender_Data_Male_Rank":166.0,"population_by_gender_Data_Female_Rank":169.0,"Age_Diversity_Index_Rank":155.0,"Employment_Health_Index_Rank":28.0,"Annual_Earnings_Index_Rank":106.0,"Housing_Affordability_Index_Rank":168.0,"Crime_Rate_Index_Rank":196.0,"Young_Index_Rank":174.0,"Middle_Aged_Index_Rank":164.0,"Old_Index_Rank":146.0}
{"neighbourhood_id":166,"population_density_Rank":17.0,"population_by_gender_Data_Male_Rank":233.0,"population_by_gender_Data_Female_Rank":234.0,"Age_Diversity_Index_Rank":230.0,"Employment_Health_Index_Rank":3.0,"Annual_Earnings_Index_Rank":229.0,"Housing_Affordability_Index_Rank":234.0,"Crime_Rate_Index_Rank":179.0,"Young_Index_Rank":233.0,"Middle_Aged_Index_Rank":234.0,"Old_Index_Rank":233.0}
{"neighbourhood_id":167,"population_density_Rank":220.0,"population_by_gender_Data_Male_Rank":196.0,"population_by_gender_Data_Female_Rank":202.0,"Age_Diversity_Index_Rank":202.0,"Employment_Health_Index_Rank":41.0,"Annual_Earnings_Index_Rank":191.0,"Housing_Affordability_Index_Rank":99.0,"Crime_Rate_Index_Rank":199.0,"Young_Index_Rank":194.0,"Middle_Aged_Index_Rank":199.0,"Old_Index_Rank":214.0}
{"neighbourhood_id":168,"population_density_Rank":121.0,"population_by_gender_Data_Male_Rank":13.0,"population_by_gender_Data_Female_Rank":33.0,"Age_Diversity_Index_Rank":60.0,"Employment_Health_Index_Rank":50.0,"Annual_Earnings_Index_Rank":21.0,"Housing_Affordability_Index_Rank":97.0,"Crime_Rate_Index_Rank":160.0,"Young_Index_Rank":45.0,"Middle_Aged_Index_Rank":13.0,"Old_Index_Rank":37.0}
{"neighbourhood_id":169,"population_density_Rank":220.0,"population_by_gender_Data_Male_Rank":196.0,"population_by_gender_Data_Female_Rank":202.0,"Age_Diversity_Index_Rank":202.0,"Employment_Health_Index_Rank":41.0,"Annual_Earnings_Index_Rank":191.0,"Housing_Affordability_Index_Rank":99.0,"Crime_Rate_Index_Rank":199.0,"Young_Index_Rank":194.0,"Middle_Aged_Index_Rank":199.0,"Old_Index_Rank":214.0}
{"neighbourhood_id":171,"population_density_Rank":114.0,"population_by_gender_Data_Male_Rank":144.0,"population_by_gender_Data_Female_Rank":163.0,"Age_Diversity_Index_Rank":200.0,"Employment_Health_Index_Rank":79.0,"Annual_Earnings_Index_Rank":178.0,"Housing_Affordability_Index_Rank":193.0,"Crime_Rate_Index_Rank":75.0,"Young_Index_Rank":134.0,"Middle_Aged_Index_Rank":163.0,"Old_Index_Rank":167.0}
{"neighbourhood_id":172,"population_density_Rank":97.0,"population_by_gender_Data_Male_Rank":110.0,"population_by_gender_Data_Female_Rank":107.0,"Age_Diversity_Index_Rank":187.0,"Employment_Health_Index_Rank":121.0,"Annual_Earnings_Index_Rank":100.0,"Housing_Affordability_Index_Rank":87.0,"Crime_Rate_Index_Rank":209.0,"Young_Index_Rank":102.0,"Middle_Aged_Index_Rank":111.0,"Old_Index_Rank":108.0}
{"neighbourhood_id":173,"population_density_Rank":15.0,"population_by_gender_Data_Male_Rank":65.0,"population_by_gender_Data_Female_Rank":86.0,"Age_Diversity_Index_Rank":99.0,"Employment_Health_Index_Rank":48.0,"Annual_Earnings_Index_Rank":67.0,"Housing_Affordability_Index_Rank":147.0,"Crime_Rate_Index_Rank":10.0,"Young_Index_Rank":92.0,"Middle_Aged_Index_Rank":48.0,"Old_Index_Rank":58.0}
{"neighbourhood_id":174,"population_density_Rank":44.0,"population_by_gender_Data_Male_Rank":3.0,"population_by_gender_Data_Female_Rank":16.0,"Age_Diversity_Index_Rank":30.0,"Employment_Health_Index_Rank":108.0,"Annual_Earnings_Index_Rank":27.0,"Housing_Affordability_Index_Rank":127.0,"Crime_Rate_Index_Rank":55.0,"Young_Index_Rank":28.0,"Middle_Aged_Index_Rank":1.0,"Old_Index_Rank":32.0}
{"neighbourhood_id":175,"population_density_Rank":93.0,"population_by_gender_Data_Male_Rank":1.0,"population_by_gender_Data_Female_Rank":8.0,"Age_Diversity_Index_Rank":3.0,"Employment_Health_Index_Rank":34.0,"Annual_Earnings_Index_Rank":46.0,"Housing_Affordability_Index_Rank":103.0,"Crime_Rate_Index_Rank":100.0,"Young_Index_Rank":1.0,"Middle_Aged_Index_Rank":5.0,"Old_Index_Rank":61.0}
{"neighbourhood_id":176,"population_density_Rank":198.0,"population_by_gender_Data_Male_Rank":172.0,"population_by_gender_Data_Female_Rank":180.0,"Age_Diversity_Index_Rank":215.0,"Employment_Health_Index_Rank":100.0,"Annual_Earnings_Index_Rank":164.0,"Housing_Affordability_Index_Rank":205.0,"Crime_Rate_Index_Rank":170.0,"Young_Index_Rank":170.0,"Middle_Aged_Index_Rank":167.0,"Old_Index_Rank":162.0}
{"neighbourhood_id":177,"population_density_Rank":145.0,"population_by_gender_Data_Male_Rank":5.0,"population_by_gender_Data_Female_Rank":15.0,"Age_Diversity_Index_Rank":54.0,"Employment_Health_Index_Rank":136.0,"Annual_Earnings_Index_Rank":14.0,"Housing_Affordability_Index_Rank":116.0,"Crime_Rate_Index_Rank":156.0,"Young_Index_Rank":24.0,"Middle_Aged_Index_Rank":7.0,"Old_Index_Rank":36.0}
{"neighbourhood_id":178,"population_density_Rank":184.0,"population_by_gender_Data_Male_Rank":176.0,"population_by_gender_Data_Female_Rank":172.0,"Age_Diversity_Index_Rank":139.0,"Employment_Health_Index_Rank":163.0,"Annual_Earnings_Index_Rank":133.0,"Housing_Affordability_Index_Rank":201.0,"Crime_Rate_Index_Rank":222.0,"Young_Index_Rank":191.0,"Middle_Aged_Index_Rank":161.0,"Old_Index_Rank":113.0}
{"neighbourhood_id":179,"population_density_Rank":184.0,"population_by_gender_Data_Male_Rank":176.0,"population_by_gender_Data_Female_Rank":172.0,"Age_Diversity_Index_Rank":139.0,"Employment_Health_Index_Rank":163.0,"Annual_Earnings_Index_Rank":133.0,"Housing_Affordability_Index_Rank":201.0,"Crime_Rate_Index_Rank":222.0,"Young_Index_Rank":191.0,"Middle_Aged_Index_Rank":161.0,"Old_Index_Rank":113.0}
{"neighbourhood_id":184,"population_density_Rank":82.0,"population_by_gender_Data_Male_Rank":130.0,"population_by_gender_Data_Female_Rank":133.0,"Age_Diversity_Index_Rank":103.0,"Employment_Health_Index_Rank":71.0,"Annual_Earnings_Index_Rank":79.0,"Housing_Affordability_Index_Rank":170.0,"Crime_Rate_Index_Rank":163.0,"Young_Index_Rank":169.0,"Middle_Aged_Index_Rank":121.0,"Old_Index_Rank":73.0}
{"neighbourhood_id":185,"population_density_Rank":126.0,"population_by_gender_Data_Male_Rank":71.0,"population_by_gender_Data_Female_Rank":70.0,"Age_Diversity_Index_Rank":29.0,"Employment_Health_Index_Rank":69.0,"Annual_Earnings_Index_Rank":10.0,"Housing_Affordability_Index_Rank":163.0,"Crime_Rate_Index_Rank":189.0,"Young_Index_Rank":120.0,"Middle_Aged_Index_Rank":40.0,"Old_Index_Rank":8.0}
{"neighbourhood_id":186,"population_density_Rank":193.0,"population_by_gender_Data_Male_Rank":206.0,"population_by_gender_Data_Female_Rank":211.0,"Age_Diversity_Index_Rank":217.0,"Employment_Health_Index_Rank":63.0,"Annual_Earnings_Index_Rank":211.0,"Housing_Affordability_Index_Rank":203.0,"Crime_Rate_Index_Rank":224.0,"Young_Index_Rank":201.0,"Middle_Aged_Index_Rank":204.0,"Old_Index_Rank":210.0}
{"neighbourhood_id":187,"population_density_Rank":194.0,"population_by_gender_Data_Male_Rank":157.0,"population_by_gender_Data_Female_Rank":152.0,"Age_Diversity_Index_Rank":83.0,"Employment_Health_Index_Rank":142.0,"Annual_Earnings_Index_Rank":118.0,"Housing_Affordability_Index_Rank":224.0,"Crime_Rate_Index_Rank":228.0,"Young_Index_Rank":183.0,"Middle_Aged_Index_Rank":142.0,"Old_Index_Rank":55.0}
{"neighbourhood_id":188,"population_density_Rank":199.0,"population_by_gender_Data_Male_Rank":217.0,"population_by_gender_Data_Female_Rank":215.0,"Age_Diversity_Index_Rank":127.0,"Employment_Health_Index_Rank":154.0,"Annual_Earnings_Index_Rank":202.0,"Housing_Affordability_Index_Rank":225.0,"Crime_Rate_Index_Rank":234.0,"Young_Index_Rank":225.0,"Middle_Aged_Index_Rank":216.0,"Old_Index_Rank":141.0}
{"neighbourhood_id":189,"population_density_Rank":176.0,"population_by_gender_Data_Male_Rank":161.0,"population_by_gender_Data_Female_Rank":164.0,"Age_Diversity_Index_Rank":149.0,"Employment_Health_Index_Rank":113.0,"Annual_Earnings_Index_Rank":141.0,"Housing_Affordability_Index_Rank":210.0,"Crime_Rate_Index_Rank":225.0,"Young_Index_Rank":178.0,"Middle_Aged_Index_Rank":139.0,"Old_Index_Rank":126.0}
{"neighbourhood_id":190,"population_density_Rank":176.0,"population_by_gender_Data_Male_Rank":161.0,"population_by_gender_Data_Female_Rank":164.0,"Age_Diversity_Index_Rank":149.0,"Employment_Health_Index_Rank":113.0,"Annual_Earnings_Index_Rank":141.0,"Housing_Affordability_Index_Rank":210.0,"Crime_Rate_Index_Rank":225.0,"Young_Index_Rank":178.0,"Middle_Aged_Index_Rank":139.0,"Old_Index_Rank":126.0}
{"neighbourhood_id":191,"population_density_Rank":77.0,"population_by_gender_Data_Male_Rank":25.0,"population_by_gender_Data_Female_Rank":35.0,"Age_Diversity_Index_Rank":27.0,"Employment_Health_Index_Rank":166.0,"Annual_Earnings_Index_Rank":58.0,"Housing_Affordability_Index_Rank":112.0,"Crime_Rate_Index_Rank":65.0,"Young_Index_Rank":68.0,"Middle_Aged_Index_Rank":10.0,"Old_Index_Rank":18.0}
{"neighbourhood_id":192,"population_density_Rank":152.0,"population_by_gender_Data_Male_Rank":106.0,"population_by_gender_Data_Female_Rank":99.0,"Age_Diversity_Index_Rank":61.0,"Employment_Health_Index_Rank":153.0,"Annual_Earnings_Index_Rank":88.0,"Housing_Affordability_Index_Rank":148.0,"Crime_Rate_Index_Rank":52.0,"Young_Index_Rank":143.0,"Middle_Aged_Index_Rank":80.0,"Old_Index_Rank":31.0}
{"neighbourhood_id":193,"population_density_Rank":97.0,"population_by_gender_Data_Male_Rank":110.0,"population_by_gender_Data_Female_Rank":107.0,"Age_Diversity_Index_Rank":187.0,"Employment_Health_Index_Rank":121.0,"Annual_Earnings_Index_Rank":100.0,"Housing_Affordability_Index_Rank":87.0,"Crime_Rate_Index_Rank":235.0,"Young_Index_Rank":102.0,"Middle_Aged_Index_Rank":111.0,"Old_Index_Rank":108.0}
{"neighbourhood_id":194,"population_density_Rank":77.0,"population_by_gender_Data_Male_Rank":25.0,"population_by_gender_Data_Female_Rank":35.0,"Age_Diversity_Index_Rank":27.0,"Employment_Health_Index_Rank":166.0,"Annual_Earnings_Index_Rank":58.0,"Housing_Affordability_Index_Rank":112.0,"Crime_Rate_Index_Rank":65.0,"Young_Index_Rank":68.0,"Middle_Aged_Index_Rank":10.0,"Old_Index_Rank":18.0}
{"neighbourhood_id":195,"population_density_Rank":183.0,"population_by_gender_Data_Male_Rank":139.0,"population_by_gender_Data_Female_Rank":142.0,"Age_Diversity_Index_Rank":218.0,"Employment_Health_Index_Rank":111.0,"Annual_Earnings_Index_Rank":144.0,"Housing_Affordability_Index_Rank":161.0,"Crime_Rate_Index_Rank":159.0,"Young_Index_Rank":125.0,"Middle_Aged_Index_Rank":160.0,"Old_Index_Rank":136.0}
{"neighbourhood_id":196,"population_density_Rank":201.0,"population_by_gender_Data_Male_Rank":222.0,"population_by_gender_Data_Female_Rank":224.0,"Age_Diversity_Index_Rank":226.0,"Employment_Health_Index_Rank":109.0,"Annual_Earnings_Index_Rank":223.0,"Housing_Affordability_Index_Rank":230.0,"Crime_Rate_Index_Rank":201.0,"Young_Index_Rank":222.0,"Middle_Aged_Index_Rank":222.0,"Old_Index_Rank":217.0}
{"neighbourhood_id":197,"population_density_Rank":201.0,"population_by_gender_Data_Male_Rank":222.0,"population_by_gender_Data_Female_Rank":224.0,"Age_Diversity_Index_Rank":226.0,"Employment_Health_Index_Rank":109.0,"Annual_Earnings_Index_Rank":223.0,"Housing_Affordability_Index_Rank":230.0,"Crime_Rate_Index_Rank":201.0,"Young_Index_Rank":222.0,"Middle_Aged_Index_Rank":222.0,"Old_Index_Rank":217.0}
{"neighbourhood_id":198,"population_density_Rank":141.0,"population_by_gender_Data_Male_Rank":76.0,"population_by_gender_Data_Female_Rank":96.0,"Age_Diversity_Index_Rank":132.0,"Employment_Health_Index_Rank":101.0,"Annual_Earnings_Index_Rank":93.0,"Housing_Affordability_Index_Rank":156.0,"Crime_Rate_Index_Rank":161.0,"Young_Index_Rank":80.0,"Middle_Aged_Index_Rank":83.0,"Old_Index_Rank":77.0}
{"neighbourhood_id":199,"population_density_Rank":120.0,"population_by_gender_Data_Male_Rank":99.0,"population_by_gender_Data_Female_Rank":113.0,"Age_Diversity_Index_Rank":145.0,"Employment_Health_Index_Rank":62.0,"Annual_Earnings_Index_Rank":83.0,"Housing_Affordability_Index_Rank":164.0,"Crime_Rate_Index_Rank":32.0,"Young_Index_Rank":100.0,"Middle_Aged_Index_Rank":106.0,"Old_Index_Rank":130.0}
{"neighbourhood_id":201,"population_density_Rank":189.0,"population_by_gender_Data_Male_Rank":207.0,"population_by_gender_Data_Female_Rank":209.0,"Age_Diversity_Index_Rank":212.0,"Employment_Health_Index_Rank":93.0,"Annual_Earnings_Index_Rank":189.0,"Housing_Affordability_Index_Rank":220.0,"Crime_Rate_Index_Rank":220.0,"Young_Index_Rank":207.0,"Middle_Aged_Index_Rank":201.0,"Old_Index_Rank":198.0}
{"neighbourhood_id":202,"population_density_Rank":129.0,"population_by_gender_Data_Male_Rank":216.0,"population_by_gender_Data_Female_Rank":216.0,"Age_Diversity_Index_Rank":222.0,"Employment_Health_Index_Rank":38.0,"Annual_Earnings_Index_Rank":193.0,"Housing_Affordability_Index_Rank":207.0,"Crime_Rate_Index_Rank":99.0,"Young_Index_Rank":220.0,"Middle_Aged_Index_Rank":215.0,"Old_Index_Rank":208.0}
{"neighbourhood_id":203,"population_density_Rank":163.0,"population_by_gender_Data_Male_Rank":164.0,"population_by_gender_Data_Female_Rank":175.0,"Age_Diversity_Index_Rank":173.0,"Employment_Health_Index_Rank":51.0,"Annual_Earnings_Index_Rank":173.0,"Housing_Affordability_Index_Rank":198.0,"Crime_Rate_Index_Rank":124.0,"Young_Index_Rank":150.0,"Middle_Aged_Index_Rank":168.0,"Old_Index_Rank":196.0}
{"neighbourhood_id":204,"population_density_Rank":92.0,"population_by_gender_Data_Male_Rank":120.0,"population_by_gender_Data_Female_Rank":132.0,"Age_Diversity_Index_Rank":87.0,"Employment_Health_Index_Rank":84.0,"Annual_Earnings_Index_Rank":149.0,"Housing_Affordability_Index_Rank":209.0,"Crime_Rate_Index_Rank":187.0,"Young_Index_Rank":112.0,"Middle_Aged_Index_Rank":120.0,"Old_Index_Rank":180.0}
{"neighbourhood_id":205,"population_density_Rank":111.0,"population_by_gender_Data_Male_Rank":200.0,"population_by_gender_Data_Female_Rank":206.0,"Age_Diversity_Index_Rank":204.0,"Employment_Health_Index_Rank":98.0,"Annual_Earnings_Index_Rank":212.0,"Housing_Affordability_Index_Rank":216.0,"Crime_Rate_Index_Rank":207.0,"Young_Index_Rank":188.0,"Middle_Aged_Index_Rank":207.0,"Old_Index_Rank":219.0}
{"neighbourhood_id":206,"population_density_Rank":137.0,"population_by_gender_Data_Male_Rank":143.0,"population_by_gender_Data_Female_Rank":159.0,"Age_Diversity_Index_Rank":161.0,"Employment_Health_Index_Rank":53.0,"Annual_Earnings_Index_Rank":148.0,"Housing_Affordability_Index_Rank":204.0,"Crime_Rate_Index_Rank":185.0,"Young_Index_Rank":133.0,"Middle_Aged_Index_Rank":149.0,"Old_Index_Rank":186.0}
{"neighbourhood_id":207,"population_density_Rank":166.0,"population_by_gender_Data_Male_Rank":125.0,"population_by_gender_Data_Female_Rank":134.0,"Age_Diversity_Index_Rank":126.0,"Employment_Health_Index_Rank":64.0,"Annual_Earnings_Index_Rank":126.0,"Housing_Affordability_Index_Rank":215.0,"Crime_Rate_Index_Rank":181.0,"Young_Index_Rank":124.0,"Middle_Aged_Index_Rank":126.0,"Old_Index_Rank":164.0}
{"neighbourhood_id":208,"population_density_Rank":111.0,"population_by_gender_Data_Male_Rank":200.0,"population_by_gender_Data_Female_Rank":206.0,"Age_Diversity_Index_Rank":204.0,"Employment_Health_Index_Rank":98.0,"Annual_Earnings_Index_Rank":212.0,"Housing_Affordability_Index_Rank":216.0,"Crime_Rate_Index_Rank":207.0,"Young_Index_Rank":188.0,"Middle_Aged_Index_Rank":207.0,"Old_Index_Rank":219.0}
{"neighbourhood_id":209,"population_density_Rank":209.0,"population_by_gender_Data_Male_Rank":202.0,"population_by_gender_Data_Female_Rank":194.0,"Age_Diversity_Index_Rank":135.0,"Employment_Health_Index_Rank":144.0,"Annual_Earnings_Index_Rank":179.0,"Housing_Affordability_Index_Rank":222.0,"Crime_Rate_Index_Rank":218.0,"Young_Index_Rank":210.0,"Middle_Aged_Index_Rank":195.0,"Old_Index_Rank":120.0}
{"neighbourhood_id":210,"population_density_Rank":209.0,"population_by_gender_Data_Male_Rank":202.0,"population_by_gender_Data_Female_Rank":194.0,"Age_Diversity_Index_Rank":135.0,"Employment_Health_Index_Rank":144.0,"Annual_Earnings_Index_Rank":179.0,"Housing_Affordability_Index_Rank":222.0,"Crime_Rate_Index_Rank":218.0,"Young_Index_Rank":210.0,"Middle_Aged_Index_Rank":195.0,"Old_Index_Rank":120.0}
{"neighbourhood_id":211,"population_density_Rank":176.0,"population_by_gender_Data_Male_Rank":161.0,"population_by_gender_Data_Female_Rank":164.0,"Age_Diversity_Index_Rank":149.0,"Employment_Health_Index_Rank":113.0,"Annual_Earnings_Index_Rank":141.0,"Housing_Affordability_Index_Rank":210.0,"Crime_Rate_Index_Rank":225.0,"Young_Index_Rank":178.0,"Middle_Aged_Index_Rank":139.0,"Old_Index_Rank":126.0}
{"neighbourhood_id":212,"population_density_Rank":186.0,"population_by_gender_Data_Male_Rank":193.0,"population_by_gender_Data_Female_Rank":190.0,"Age_Diversity_Index_Rank":196.0,"Employment_Health_Index_Rank":65.0,"Annual_Earnings_Index_Rank":175.0,"Housing_Affordability_Index_Rank":226.0,"Crime_Rate_Index_Rank":186.0,"Young_Index_Rank":198.0,"Middle_Aged_Index_Rank":185.0,"Old_Index_Rank":163.0}
{"neighbourhood_id":214,"population_density_Rank":189.0,"population_by_gender_Data_Male_Rank":207.0,"population_by_gender_Data_Female_Rank":209.0,"Age_Diversity_Index_Rank":212.0,"Employment_Health_Index_Rank":93.0,"Annual_Earnings_Index_Rank":189.0,"Housing_Affordability_Index_Rank":220.0,"Crime_Rate_Index_Rank":220.0,"Young_Index_Rank":207.0,"Middle_Aged_Index_Rank":201.0,"Old_Index_Rank":198.0}
{"neighbourhood_id":216,"population_density_Rank":171.0,"population_by_gender_Data_Male_Rank":184.0,"population_by_gender_Data_Female_Rank":178.0,"Age_Diversity_Index_Rank":208.0,"Employment_Health_Index_Rank":118.0,"Annual_Earnings_Index_Rank":197.0,"Housing_Affordability_Index_Rank":109.0,"Crime_Rate_Index_Rank":25.0,"Young_Index_Rank":154.0,"Middle_Aged_Index_Rank":189.0,"Old_Index_Rank":181.0}
{"neighbourhood_id":217,"population_density_Rank":171.0,"population_by_gender_Data_Male_Rank":184.0,"population_by_gender_Data_Female_Rank":178.0,"Age_Diversity_Index_Rank":208.0,"Employment_Health_Index_Rank":118.0,"Annual_Earnings_Index_Rank":197.0,"Housing_Affordability_Index_Rank":109.0,"Crime_Rate_Index_Rank":25.0,"Young_Index_Rank":154.0,"Middle_Aged_Index_Rank":189.0,"Old_Index_Rank":181.0}
{"neighbourhood_id":218,"population_density_Rank":181.0,"population_by_gender_Data_Male_Rank":104.0,"population_by_gender_Data_Female_Rank":84.0,"Age_Diversity_Index_Rank":115.0,"Employment_Health_Index_Rank":60.0,"Annual_Earnings_Index_Rank":62.0,"Housing_Affordability_Index_Rank":139.0,"Crime_Rate_Index_Rank":8.0,"Young_Index_Rank":85.0,"Middle_Aged_Index_Rank":91.0,"Old_Index_Rank":71.0}
{"neighbourhood_id":219,"population_density_Rank":181.0,"population_by_gender_Data_Male_Rank":104.0,"population_by_gender_Data_Female_Rank":84.0,"Age_Diversity_Index_Rank":115.0,"Employment_Health_Index_Rank":60.0,"Annual_Earnings_Index_Rank":62.0,"Housing_Affordability_Index_Rank":139.0,"Crime_Rate_Index_Rank":8.0,"Young_Index_Rank":85.0,"Middle_Aged_Index_Rank":91.0,"Old_Index_Rank":71.0}
{"neighbourhood_id":220,"population_density_Rank":168.0,"population_by_gender_Data_Male_Rank":180.0,"population_by_gender_Data_Female_Rank":167.0,"Age_Diversity_Index_Rank":184.0,"Employment_Health_Index_Rank":57.0,"Annual_Earnings_Index_Rank":150.0,"Housing_Affordability_Index_Rank":213.0,"Crime_Rate_Index_Rank":140.0,"Young_Index_Rank":164.0,"Middle_Aged_Index_Rank":172.0,"Old_Index_Rank":156.0}
{"neighbourhood_id":221,"population_density_Rank":167.0,"population_by_gender_Data_Male_Rank":190.0,"population_by_gender_Data_Female_Rank":189.0,"Age_Diversity_Index_Rank":197.0,"Employment_Health_Index_Rank":80.0,"Annual_Earnings_Index_Rank":184.0,"Housing_Affordability_Index_Rank":189.0,"Crime_Rate_Index_Rank":190.0,"Young_Index_Rank":187.0,"Middle_Aged_Index_Rank":184.0,"Old_Index_Rank":179.0}
{"neighbourhood_id":226,"population_density_Rank":168.0,"population_by_gender_Data_Male_Rank":180.0,"population_by_gender_Data_Female_Rank":167.0,"Age_Diversity_Index_Rank":184.0,"Employment_Health_Index_Rank":57.0,"Annual_Earnings_Index_Rank":150.0,"Housing_Affordability_Index_Rank":213.0,"Crime_Rate_Index_Rank":140.0,"Young_Index_Rank":164.0,"Middle_Aged_Index_Rank":172.0,"Old_Index_Rank":156.0}
{"neighbourhood_id":227,"population_density_Rank":200.0,"population_by_gender_Data_Male_Rank":169.0,"population_by_gender_Data_Female_Rank":147.0,"Age_Diversity_Index_Rank":144.0,"Employment_Health_Index_Rank":49.0,"Annual_Earnings_Index_Rank":113.0,"Housing_Affordability_Index_Rank":219.0,"Crime_Rate_Index_Rank":174.0,"Young_Index_Rank":149.0,"Middle_Aged_Index_Rank":154.0,"Old_Index_Rank":142.0}
{"neighbourhood_id":230,"population_density_Rank":170.0,"population_by_gender_Data_Male_Rank":85.0,"population_by_gender_Data_Female_Rank":93.0,"Age_Diversity_Index_Rank":162.0,"Employment_Health_Index_Rank":194.0,"Annual_Earnings_Index_Rank":140.0,"Housing_Affordability_Index_Rank":35.0,"Crime_Rate_Index_Rank":91.0,"Young_Index_Rank":70.0,"Middle_Aged_Index_Rank":110.0,"Old_Index_Rank":75.0}
{"neighbourhood_id":231,"population_density_Rank":179.0,"population_by_gender_Data_Male_Rank":218.0,"population_by_gender_Data_Female_Rank":217.0,"Age_Diversity_Index_Rank":219.0,"Employment_Health_Index_Rank":192.0,"Annual_Earnings_Index_Rank":221.0,"Housing_Affordability_Index_Rank":166.0,"Crime_Rate_Index_Rank":205.0,"Young_Index_Rank":205.0,"Middle_Aged_Index_Rank":219.0,"Old_Index_Rank":221.0}
{"neighbourhood_id":232,"population_density_Rank":191.0,"population_by_gender_Data_Male_Rank":213.0,"population_by_gender_Data_Female_Rank":213.0,"Age_Diversity_Index_Rank":194.0,"Employment_Health_Index_Rank":159.0,"Annual_Earnings_Index_Rank":200.0,"Housing_Affordability_Index_Rank":190.0,"Crime_Rate_Index_Rank":232.0,"Young_Index_Rank":216.0,"Middle_Aged_Index_Rank":210.0,"Old_Index_Rank":184.0}
{"neighbourhood_id":233,"population_density_Rank":179.0,"population_by_gender_Data_Male_Rank":218.0,"population_by_gender_Data_Female_Rank":217.0,"Age_Diversity_Index_Rank":219.0,"Employment_Health_Index_Rank":192.0,"Annual_Earnings_Index_Rank":221.0,"Housing_Affordability_Index_Rank":166.0,"Crime_Rate_Index_Rank":205.0,"Young_Index_Rank":205.0,"Middle_Aged_Index_Rank":219.0,"Old_Index_Rank":221.0}
{"neighbourhood_id":234,"population_density_Rank":97.0,"population_by_gender_Data_Male_Rank":110.0,"population_by_gender_Data_Female_Rank":107.0,"Age_Diversity_Index_Rank":187.0,"Employment_Health_Index_Rank":121.0,"Annual_Earnings_Index_Rank":100.0,"Housing_Affordability_Index_Rank":87.0,"Crime_Rate_Index_Rank":209.0,"Young_Index_Rank":102.0,"Middle_Aged_Index_Rank":111.0,"Old_Index_Rank":108.0}
{"neighbourhood_id":235,"population_density_Rank":93.0,"population_by_gender_Data_Male_Rank":1.0,"population_by_gender_Data_Female_Rank":8.0,"Age_Diversity_Index_Rank":3.0,"Employment_Health_Index_Rank":34.0,"Annual_Earnings_Index_Rank":46.0,"Housing_Affordability_Index_Rank":103.0,"Crime_Rate_Index_Rank":100.0,"Young_Index_Rank":1.0,"Middle_Aged_Index_Rank":5.0,"Old_Index_Rank":61.0}
{"neighbourhood_id":236,"population_density_Rank":163.0,"population_by_gender_Data_Male_Rank":164.0,"population_by_gender_Data_Female_Rank":175.0,"Age_Diversity_Index_Rank":173.0,"Employment_Health_Index_Rank":51.0,"Annual_Earnings_Index_Rank":173.0,"Housing_Affordability_Index_Rank":198.0,"Crime_Rate_Index_Rank":124.0,"Young_Index_Rank":150.0,"Middle_Aged_Index_Rank":168.0,"Old_Index_Rank":196.0}
{"neighbourhood_id":237,"population_density_Rank":97.0,"population_by_gender_Data_Male_Rank":236.0,"population_by_gender_Data_Female_Rank":236.0,"Age_Diversity_Index_Rank":236.0,"Employment_Health_Index_Rank":229.0,"Annual_Earnings_Index_Rank":236.0,"Housing_Affordability_Index_Rank":87.0,"Crime_Rate_Index_Rank":229.0,"Young_Index_Rank":236.0,"Middle_Aged_Index_Rank":236.0,"Old_Index_Rank":236.0}
{"neighbourhood_id":238,"population_density_Rank":204.0,"population_by_gender_Data_Male_Rank":226.0,"population_by_gender_Data_Female_Rank":226.0,"Age_Diversity_Index_Rank":228.0,"Employment_Health_Index_Rank":195.0,"Annual_Earnings_Index_Rank":226.0,"Housing_Affordability_Index_Rank":180.0,"Crime_Rate_Index_Rank":126.0,"Young_Index_Rank":224.0,"Middle_Aged_Index_Rank":224.0,"Old_Index_Rank":226.0}
{"neighbourhood_id":239,"population_density_Rank":234.0,"population_by_gender_Data_Male_Rank":234.0,"population_by_gender_Data_Female_Rank":233.0,"Age_Diversity_Index_Rank":232.0,"Employment_Health_Index_Rank":200.0,"Annual_Earnings_Index_Rank":235.0,"Housing_Affordability_Index_Rank":236.0,"Crime_Rate_Index_Rank":236.0,"Young_Index_Rank":234.0,"Middle_Aged_Index_Rank":233.0,"Old_Index_Rank":227.0}
{"neighbourhood_id":240,"population_density_Rank":211.0,"population_by_gender_Data_Male_Rank":145.0,"population_by_gender_Data_Female_Rank":153.0,"Age_Diversity_Index_Rank":180.0,"Employment_Health_Index_Rank":155.0,"Annual_Earnings_Index_Rank":153.0,"Housing_Affordability_Index_Rank":149.0,"Crime_Rate_Index_Rank":18.0,"Young_Index_Rank":138.0,"Middle_Aged_Index_Rank":150.0,"Old_Index_Rank":158.0}
{"neighbourhood_id":241,"population_density_Rank":211.0,"population_by_gender_Data_Male_Rank":145.0,"population_by_gender_Data_Female_Rank":153.0,"Age_Diversity_Index_Rank":180.0,"Employment_Health_Index_Rank":155.0,"Annual_Earnings_Index_Rank":153.0,"Housing_Affordability_Index_Rank":149.0,"Crime_Rate_Index_Rank":18.0,"Young_Index_Rank":138.0,"Middle_Aged_Index_Rank":150.0,"Old_Index_Rank":158.0}
{"neighbourhood_id":242,"population_density_Rank":216.0,"population_by_gender_Data_Male_Rank":131.0,"population_by_gender_Data_Female_Rank":143.0,"Age_Diversity_Index_Rank":157.0,"Employment_Health_Index_Rank":181.0,"Annual_Earnings_Index_Rank":122.0,"Housing_Affordability_Index_Rank":172.0,"Crime_Rate_Index_Rank":192.0,"Young_Index_Rank":145.0,"Middle_Aged_Index_Rank":128.0,"Old_Index_Rank":131.0}
{"neighbourhood_id":243,"population_density_Rank":211.0,"population_by_gender_Data_Male_Rank":145.0,"population_by_gender_Data_Female_Rank":153.0,"Age_Diversity_Index_Rank":180.0,"Employment_Health_Index_Rank":155.0,"Annual_Earnings_Index_Rank":153.0,"Housing_Affordability_Index_Rank":149.0,"Crime_Rate_Index_Rank":18.0,"Young_Index_Rank":138.0,"Middle_Aged_Index_Rank":150.0,"Old_Index_Rank":158.0}
{"neighbourhood_id":244,"population_density_Rank":195.0,"population_by_gender_Data_Male_Rank":204.0,"population_by_gender_Data_Female_Rank":200.0,"Age_Diversity_Index_Rank":214.0,"Employment_Health_Index_Rank":131.0,"Annual_Earnings_Index_Rank":199.0,"Housing_Affordability_Index_Rank":192.0,"Crime_Rate_Index_Rank":166.0,"Young_Index_Rank":190.0,"Middle_Aged_Index_Rank":205.0,"Old_Index_Rank":213.0}
{"neighbourhood_id":245,"population_density_Rank":188.0,"population_by_gender_Data_Male_Rank":215.0,"population_by_gender_Data_Female_Rank":219.0,"Age_Diversity_Index_Rank":221.0,"Employment_Health_Index_Rank":177.0,"Annual_Earnings_Index_Rank":219.0,"Housing_Affordability_Index_Rank":206.0,"Crime_Rate_Index_Rank":88.0,"Young_Index_Rank":203.0,"Middle_Aged_Index_Rank":218.0,"Old_Index_Rank":225.0}
{"neighbourhood_id":246,"population_density_Rank":224.0,"population_by_gender_Data_Male_Rank":198.0,"population_by_gender_Data_Female_Rank":198.0,"Age_Diversity_Index_Rank":168.0,"Employment_Health_Index_Rank":180.0,"Annual_Earnings_Index_Rank":203.0,"Housing_Affordability_Index_Rank":146.0,"Crime_Rate_Index_Rank":182.0,"Young_Index_Rank":173.0,"Middle_Aged_Index_Rank":203.0,"Old_Index_Rank":224.0}
{"neighbourhood_id":247,"population_density_Rank":211.0,"population_by_gender_Data_Male_Rank":145.0,"population_by_gender_Data_Female_Rank":153.0,"Age_Diversity_Index_Rank":180.0,"Employment_Health_Index_Rank":155.0,"Annual_Earnings_Index_Rank":153.0,"Housing_Affordability_Index_Rank":149.0,"Crime_Rate_Index_Rank":18.0,"Young_Index_Rank":138.0,"Middle_Aged_Index_Rank":150.0,"Old_Index_Rank":158.0}
{"neighbourhood_id":248,"population_density_Rank":216.0,"population_by_gender_Data_Male_Rank":131.0,"population_by_gender_Data_Female_Rank":143.0,"Age_Diversity_Index_Rank":157.0,"Employment_Health_Index_Rank":181.0,"Annual_Earnings_Index_Rank":122.0,"Housing_Affordability_Index_Rank":172.0,"Crime_Rate_Index_Rank":192.0,"Young_Index_Rank":145.0,"Middle_Aged_Index_Rank":128.0,"Old_Index_Rank":131.0}
{"neighbourhood_id":249,"population_density_Rank":227.0,"population_by_gender_Data_Male_Rank":93.0,"population_by_gender_Data_Female_Rank":100.0,"Age_Diversity_Index_Rank":78.0,"Employment_Health_Index_Rank":170.0,"Annual_Earnings_Index_Rank":54.0,"Housing_Affordability_Index_Rank":185.0,"Crime_Rate_Index_Rank":130.0,"Young_Index_Rank":115.0,"Middle_Aged_Index_Rank":84.0,"Old_Index_Rank":49.0}
{"neighbourhood_id":250,"population_density_Rank":227.0,"population_by_gender_Data_Male_Rank":93.0,"population_by_gender_Data_Female_Rank":100.0,"Age_Diversity_Index_Rank":78.0,"Employment_Health_Index_Rank":170.0,"Annual_Earnings_Index_Rank":54.0,"Housing_Affordability_Index_Rank":185.0,"Crime_Rate_Index_Rank":130.0,"Young_Index_Rank":115.0,"Middle_Aged_Index_Rank":84.0,"Old_Index_Rank":49.0}
{"neighbourhood_id":251,"population_density_Rank":231.0,"population_by_gender_Data_Male_Rank":29.0,"population_by_gender_Data_Female_Rank":37.0,"Age_Diversity_Index_Rank":39.0,"Employment_Health_Index_Rank":151.0,"Annual_Earnings_Index_Rank":8.0,"Housing_Affordability_Index_Rank":176.0,"Crime_Rate_Index_Rank":203.0,"Young_Index_Rank":58.0,"Middle_Aged_Index_Rank":20.0,"Old_Index_Rank":9.0}
{"neighbourhood_id":252,"population_density_Rank":231.0,"population_by_gender_Data_Male_Rank":29.0,"population_by_gender_Data_Female_Rank":37.0,"Age_Diversity_Index_Rank":39.0,"Employment_Health_Index_Rank":151.0,"Annual_Earnings_Index_Rank":8.0,"Housing_Affordability_Index_Rank":176.0,"Crime_Rate_Index_Rank":203.0,"Young_Index_Rank":58.0,"Middle_Aged_Index_Rank":20.0,"Old_Index_Rank":9.0}
{"neighbourhood_id":253,"population_density_Rank":227.0,"population_by_gender_Data_Male_Rank":93.0,"population_by_gender_Data_Female_Rank":100.0,"Age_Diversity_Index_Rank":78.0,"Employment_Health_Index_Rank":170.0,"Annual_Earnings_Index_Rank":54.0,"Housing_Affordability_Index_Rank":185.0,"Crime_Rate_Index_Rank":130.0,"Young_Index_Rank":115.0,"Middle_Aged_Index_Rank":84.0,"Old_Index_Rank":49.0}
{"neighbourhood_id":254,"population_density_Rank":196.0,"population_by_gender_Data_Male_Rank":194.0,"population_by_gender_Data_Female_Rank":192.0,"Age_Diversity_Index_Rank":175.0,"Employment_Health_Index_Rank":102.0,"Annual_Earnings_Index_Rank":171.0,"Housing_Affordability_Index_Rank":228.0,"Crime_Rate_Index_Rank":213.0,"Young_Index_Rank":196.0,"Middle_Aged_Index_Rank":193.0,"Old_Index_Rank":168.0}
{"neighbourhood_id":259,"population_density_Rank":216.0,"population_by_gender_Data_Male_Rank":131.0,"population_by_gender_Data_Female_Rank":143.0,"Age_Diversity_Index_Rank":157.0,"Employment_Health_Index_Rank":181.0,"Annual_Earnings_Index_Rank":122.0,"Housing_Affordability_Index_Rank":172.0,"Crime_Rate_Index_Rank":192.0,"Young_Index_Rank":145.0,"Middle_Aged_Index_Rank":128.0,"Old_Index_Rank":131.0}
{"neighbourhood_id":260,"population_density_Rank":216.0,"population_by_gender_Data_Male_Rank":131.0,"population_by_gender_Data_Female_Rank":143.0,"Age_Diversity_Index_Rank":157.0,"Employment_Health_Index_Rank":181.0,"Annual_Earnings_Index_Rank":122.0,"Housing_Affordability_Index_Rank":172.0,"Crime_Rate_Index_Rank":192.0,"Young_Index_Rank":145.0,"Middle_Aged_Index_Rank":128.0,"Old_Index_Rank":131.0}
{"neighbourhood_id":261,"population_density_Rank":227.0,"population_by_gender_Data_Male_Rank":93.0,"population_by_gender_Data_Female_Rank":100.0,"Age_Diversity_Index_Rank":78.0,"Employment_Health_Index_Rank":170.0,"Annual_Earnings_Index_Rank":54.0,"Housing_Affordability_Index_Rank":185.0,"Crime_Rate_Index_Rank":130.0,"Young_Index_Rank":115.0,"Middle_Aged_Index_Rank":84.0,"Old_Index_Rank":49.0}
{"neighbourhood_id":262,"population_density_Rank":196.0,"population_by_gender_Data_Male_Rank":194.0,"population_by_gender_Data_Female_Rank":192.0,"Age_Diversity_Index_Rank":175.0,"Employment_Health_Index_Rank":102.0,"Annual_Earnings_Index_Rank":171.0,"Housing_Affordability_Index_Rank":228.0,"Crime_Rate_Index_Rank":213.0,"Young_Index_Rank":196.0,"Middle_Aged_Index_Rank":193.0,"Old_Index_Rank":168.0}
